<?xml version="1.0" encoding="UTF-8"?>
<MF0 version="1.1" packageUris="http://schema.mathworks.com/mf0/ci/19700101 http://schema.mathworks.com/mf0/sl_modelref_info/R2023a http://schema.mathworks.com/mf0/slexec_mm_sto/R2023a_202208151321 http://schema.mathworks.com/mf0/sltp_mm/R2023a_202209151115">
  <ModelRefInfoRepo.ModelRefInfoRoot type="ModelRefInfoRepo.ModelRefInfoRoot" uuid="1f2fd83e-1e2e-4803-a066-bad819eb9f64">
    <JITEngines>s1uWuYQ09HTjMB3sy2Wu0JC</JITEngines>
    <JITEngines>s4Flv9Rvvm8peBFSTz3SacH</JITEngines>
    <JITEngines>s4H4zeTilpvDvJC2vKgsmzC</JITEngines>
    <JITEngines>s4HXtdco8cChZTXjFuVIiBH</JITEngines>
    <JITEngines>s4eJoF1w2L6qtVxJoAsg8LF</JITEngines>
    <JITEngines>s6TcIRvCzHGuLmuGNi3psNF</JITEngines>
    <JITEngines>s8fpdUZoUG77VeVBcE9TlqH</JITEngines>
    <JITEngines>s8sA1KdK7dqvTJmsqWvAgCD</JITEngines>
    <JITEngines>sACH091L385pecbqeAC0hhC</JITEngines>
    <JITEngines>sAHfTSdCtCqGHlbrRcxDmF</JITEngines>
    <JITEngines>sB2GVrfADHZtxwpdQvUJCFH</JITEngines>
    <JITEngines>sDOnWJA3165e7ELT52cwhlB</JITEngines>
    <JITEngines>sEZhPw7xZMMirDlG01mJSgF</JITEngines>
    <JITEngines>sFchoxdh80Sa7XMPwn4nCKF</JITEngines>
    <JITEngines>sGxpPWrN1ZWW2U4w891MkvB</JITEngines>
    <JITEngines>sKO0LwMyTkxUJYRhwmexfwD</JITEngines>
    <JITEngines>sMCcFiVmtPXNN81ZmKqWiS</JITEngines>
    <JITEngines>sNi8gsKDleCvTT0irlUhPeC</JITEngines>
    <JITEngines>sQ9j5vRincAPlI6F64k0xtE</JITEngines>
    <JITEngines>sR0lHsrjMi6CodcYf0o1vT</JITEngines>
    <JITEngines>sReeODILU2e60x2s92CPQaF</JITEngines>
    <JITEngines>sSsYEVxRV6sM0pFa8adiLcF</JITEngines>
    <JITEngines>sT6UUwvzNcdVU5uLXuF4aYE</JITEngines>
    <JITEngines>sTjlFUKxKYImMriqEMlwuxC</JITEngines>
    <JITEngines>sTrDPeDoVvW9Btf2k1rOysG</JITEngines>
    <JITEngines>sTxuMtxOHBMq5qBJODd9UiE</JITEngines>
    <JITEngines>sUAie6jLTWMWCqcjGr5901</JITEngines>
    <JITEngines>sV5RGTKL38FA90uaSMcnrqD</JITEngines>
    <JITEngines>sWxLnt0DQpWqEwZbebZR1oD</JITEngines>
    <JITEngines>sYO6OWaKh7yFHbnY6af6LAB</JITEngines>
    <JITEngines>sYfvyduYiC4bq1FVcWn7JWH</JITEngines>
    <JITEngines>sb38BthBZjURojBY2QcD6QH</JITEngines>
    <JITEngines>sbx9UnfpaG9ajuSEQ2485YE</JITEngines>
    <JITEngines>sc8jbEyMrUfnbn4JNAYWyfB</JITEngines>
    <JITEngines>sjsq8l0isIQpiWD5HQmxZgD</JITEngines>
    <JITEngines>sjuddF3uHKabu3xJEd2OVU</JITEngines>
    <JITEngines>skJOybINynFmBinmhWyHS3</JITEngines>
    <JITEngines>skmWSnqAaF79GYZDN2aT5t</JITEngines>
    <JITEngines>slmuwPFxuc49dI4ha2KHxJH</JITEngines>
    <JITEngines>slrHvb8AwP31pUsP7QFn8eB</JITEngines>
    <JITEngines>so4tqrRuNgBDAuhZBE5ZskE</JITEngines>
    <JITEngines>sqmGjB2TB0x3rbLRTznaC3F</JITEngines>
    <JITEngines>st2zeE10SGpHFSWgCekoZ6B</JITEngines>
    <JITEngines>stglIGj3rwltbGAYe3AJ5rD</JITEngines>
    <JITEngines>suE9OCf0mMAxEGFMTUuYIhH</JITEngines>
    <JITEngines>swBPPi2Dzq19NNFAOeYn6zC</JITEngines>
    <JITEngines>swyc3X6nQFxGRaS1X35yMeE</JITEngines>
    <JITEngines>sxn6JW1HajNxGwfNdS6gXXC</JITEngines>
    <childModelRefInfo type="ModelRefInfoRepo.ChildModelRefInfo" uuid="4e4689f1-3040-459e-84b4-0daf4de8b263">
      <modelName>APF_Path_Planning_2023a</modelName>
      <modelPath>APF_Path_Planning_2023a</modelPath>
    </childModelRefInfo>
    <dataTransferInfos>AAFJTQAAAAAOAAAAOAAAAAYAAAAIAAAAAgAAAAAAAAAFAAAACAAAAAAAAAABAAAAAQAAAAAAAAAFAAQAAQAAAAEAAAAAAAAA</dataTransferInfos>
    <defaultsCMapping>{&quot;Inports&quot;:&quot;{\&quot;Name\&quot;:\&quot;Default\&quot;,\&quot;Checksum\&quot;:\&quot;Default\&quot;,\&quot;PerInstancePropertiesChecksum\&quot;:\&quot;\&quot;,\&quot;MemorySectionName\&quot;:\&quot;None\&quot;,\&quot;MemorySectionChecksum\&quot;:\&quot;None\&quot;}&quot;,&quot;Outports&quot;:&quot;{\&quot;Name\&quot;:\&quot;Default\&quot;,\&quot;Checksum\&quot;:\&quot;Default\&quot;,\&quot;PerInstancePropertiesChecksum\&quot;:\&quot;\&quot;,\&quot;MemorySectionName\&quot;:\&quot;None\&quot;,\&quot;MemorySectionChecksum\&quot;:\&quot;None\&quot;}&quot;,&quot;ParameterArguments&quot;:&quot;{\&quot;Name\&quot;:\&quot;Default\&quot;,\&quot;Checksum\&quot;:\&quot;Default\&quot;,\&quot;PerInstancePropertiesChecksum\&quot;:\&quot;\&quot;,\&quot;MemorySectionName\&quot;:\&quot;None\&quot;,\&quot;MemorySectionChecksum\&quot;:\&quot;None\&quot;}&quot;,&quot;LocalParameters&quot;:&quot;{\&quot;Name\&quot;:\&quot;Default\&quot;,\&quot;Checksum\&quot;:\&quot;Default\&quot;,\&quot;PerInstancePropertiesChecksum\&quot;:\&quot;\&quot;,\&quot;MemorySectionName\&quot;:\&quot;None\&quot;,\&quot;MemorySectionChecksum\&quot;:\&quot;None\&quot;}&quot;,&quot;GlobalParameters&quot;:&quot;{\&quot;Name\&quot;:\&quot;Default\&quot;,\&quot;Checksum\&quot;:\&quot;Default\&quot;,\&quot;PerInstancePropertiesChecksum\&quot;:\&quot;\&quot;,\&quot;MemorySectionName\&quot;:\&quot;None\&quot;,\&quot;MemorySectionChecksum\&quot;:\&quot;None\&quot;}&quot;,&quot;InternalData&quot;:&quot;{\&quot;Name\&quot;:\&quot;Default\&quot;,\&quot;Checksum\&quot;:\&quot;Default\&quot;,\&quot;PerInstancePropertiesChecksum\&quot;:\&quot;\&quot;,\&quot;MemorySectionName\&quot;:\&quot;None\&quot;,\&quot;MemorySectionChecksum\&quot;:\&quot;None\&quot;}&quot;,&quot;SharedLocalDataStores&quot;:&quot;{\&quot;Name\&quot;:\&quot;Default\&quot;,\&quot;Checksum\&quot;:\&quot;Default\&quot;,\&quot;PerInstancePropertiesChecksum\&quot;:\&quot;\&quot;,\&quot;MemorySectionName\&quot;:\&quot;None\&quot;,\&quot;MemorySectionChecksum\&quot;:\&quot;None\&quot;}&quot;,&quot;GlobalDataStores&quot;:&quot;{\&quot;Name\&quot;:\&quot;Default\&quot;,\&quot;Checksum\&quot;:\&quot;Default\&quot;,\&quot;PerInstancePropertiesChecksum\&quot;:\&quot;\&quot;,\&quot;MemorySectionName\&quot;:\&quot;None\&quot;,\&quot;MemorySectionChecksum\&quot;:\&quot;None\&quot;}&quot;,&quot;Constants&quot;:&quot;{\&quot;Name\&quot;:\&quot;Default\&quot;,\&quot;Checksum\&quot;:\&quot;Default\&quot;,\&quot;PerInstancePropertiesChecksum\&quot;:\&quot;\&quot;,\&quot;MemorySectionName\&quot;:\&quot;None\&quot;,\&quot;MemorySectionChecksum\&quot;:\&quot;None\&quot;}&quot;,&quot;DataTransfers&quot;:&quot;{\&quot;Name\&quot;:\&quot;Default\&quot;,\&quot;Checksum\&quot;:\&quot;Default\&quot;,\&quot;PerInstancePropertiesChecksum\&quot;:\&quot;\&quot;,\&quot;MemorySectionName\&quot;:\&quot;None\&quot;,\&quot;MemorySectionChecksum\&quot;:\&quot;None\&quot;}&quot;,&quot;ModelData&quot;:&quot;{\&quot;Name\&quot;:\&quot;Default\&quot;,\&quot;Checksum\&quot;:\&quot;Default\&quot;,\&quot;PerInstancePropertiesChecksum\&quot;:\&quot;\&quot;,\&quot;MemorySectionName\&quot;:\&quot;None\&quot;,\&quot;MemorySectionChecksum\&quot;:\&quot;None\&quot;}&quot;,&quot;InitializeTerminate&quot;:&quot;{\&quot;Name\&quot;:\&quot;Default\&quot;,\&quot;Checksum\&quot;:\&quot;Default\&quot;,\&quot;PerInstancePropertiesChecksum\&quot;:\&quot;\&quot;,\&quot;MemorySectionName\&quot;:\&quot;None\&quot;,\&quot;MemorySectionChecksum\&quot;:\&quot;None\&quot;}&quot;,&quot;Execution&quot;:&quot;{\&quot;Name\&quot;:\&quot;Default\&quot;,\&quot;Checksum\&quot;:\&quot;Default\&quot;,\&quot;PerInstancePropertiesChecksum\&quot;:\&quot;\&quot;,\&quot;MemorySectionName\&quot;:\&quot;None\&quot;,\&quot;MemorySectionChecksum\&quot;:\&quot;None\&quot;}&quot;,&quot;SharedUtility&quot;:&quot;{\&quot;Name\&quot;:\&quot;Default\&quot;,\&quot;Checksum\&quot;:\&quot;Default\&quot;,\&quot;PerInstancePropertiesChecksum\&quot;:\&quot;\&quot;,\&quot;MemorySectionName\&quot;:\&quot;None\&quot;,\&quot;MemorySectionChecksum\&quot;:\&quot;None\&quot;}&quot;}</defaultsCMapping>
    <fastestNoncontSigFeedingDerivPorts>.01</fastestNoncontSigFeedingDerivPorts>
    <globalVariables>Att_Mode</globalVariables>
    <globalVariables>BLACK_end</globalVariables>
    <globalVariables>BLACK_ini</globalVariables>
    <globalVariables>BLUE_end</globalVariables>
    <globalVariables>BLUE_ini</globalVariables>
    <globalVariables>Binv</globalVariables>
    <globalVariables>F_Black_X_nominal</globalVariables>
    <globalVariables>F_Black_Y_nominal</globalVariables>
    <globalVariables>F_Blue_X_nominal</globalVariables>
    <globalVariables>F_Blue_Y_nominal</globalVariables>
    <globalVariables>F_red_X_nominal</globalVariables>
    <globalVariables>F_red_Y_nominal</globalVariables>
    <globalVariables>F_thrusters_BLACK</globalVariables>
    <globalVariables>F_thrusters_BLUE</globalVariables>
    <globalVariables>F_thrusters_RED</globalVariables>
    <globalVariables>Gamma1_el</globalVariables>
    <globalVariables>Gamma1_sh</globalVariables>
    <globalVariables>Gamma1_wr</globalVariables>
    <globalVariables>Gamma2_el</globalVariables>
    <globalVariables>Gamma2_sh</globalVariables>
    <globalVariables>Gamma2_wr</globalVariables>
    <globalVariables>Gamma3_el</globalVariables>
    <globalVariables>Gamma3_sh</globalVariables>
    <globalVariables>Gamma3_wr</globalVariables>
    <globalVariables>Gamma4_el</globalVariables>
    <globalVariables>Gamma4_sh</globalVariables>
    <globalVariables>Gamma4_wr</globalVariables>
    <globalVariables>Gamma5_el</globalVariables>
    <globalVariables>Gamma5_sh</globalVariables>
    <globalVariables>Gamma5_wr</globalVariables>
    <globalVariables>Gamma6_el</globalVariables>
    <globalVariables>Gamma6_sh</globalVariables>
    <globalVariables>Gamma6_wr</globalVariables>
    <globalVariables>Hz</globalVariables>
    <globalVariables>IBLACK</globalVariables>
    <globalVariables>IBLUE</globalVariables>
    <globalVariables>IDIST</globalVariables>
    <globalVariables>IEE</globalVariables>
    <globalVariables>IPROX</globalVariables>
    <globalVariables>IRED</globalVariables>
    <globalVariables>K_a</globalVariables>
    <globalVariables>Kd_elarm</globalVariables>
    <globalVariables>Kd_sharm</globalVariables>
    <globalVariables>Kd_tb</globalVariables>
    <globalVariables>Kd_tblue</globalVariables>
    <globalVariables>Kd_tr</globalVariables>
    <globalVariables>Kd_wrarm</globalVariables>
    <globalVariables>Kd_xb</globalVariables>
    <globalVariables>Kd_xblue</globalVariables>
    <globalVariables>Kd_xr</globalVariables>
    <globalVariables>Kd_yb</globalVariables>
    <globalVariables>Kd_yblue</globalVariables>
    <globalVariables>Kd_yr</globalVariables>
    <globalVariables>Kp_elarm</globalVariables>
    <globalVariables>Kp_sharm</globalVariables>
    <globalVariables>Kp_tb</globalVariables>
    <globalVariables>Kp_tblue</globalVariables>
    <globalVariables>Kp_tr</globalVariables>
    <globalVariables>Kp_wrarm</globalVariables>
    <globalVariables>Kp_xb</globalVariables>
    <globalVariables>Kp_xblue</globalVariables>
    <globalVariables>Kp_xr</globalVariables>
    <globalVariables>Kp_yb</globalVariables>
    <globalVariables>Kp_yblue</globalVariables>
    <globalVariables>Kp_yr</globalVariables>
    <globalVariables>Method</globalVariables>
    <globalVariables>Nmat</globalVariables>
    <globalVariables>PWMFreq</globalVariables>
    <globalVariables>P_b</globalVariables>
    <globalVariables>Phase0_End</globalVariables>
    <globalVariables>Phase1_End</globalVariables>
    <globalVariables>Phase2_End</globalVariables>
    <globalVariables>Phase3_End</globalVariables>
    <globalVariables>Phase3_SubPhase1_End</globalVariables>
    <globalVariables>Phase3_SubPhase2_End</globalVariables>
    <globalVariables>Phase3_SubPhase3_End</globalVariables>
    <globalVariables>Phase3_SubPhase4_End</globalVariables>
    <globalVariables>Phase4_End</globalVariables>
    <globalVariables>Phase5_End</globalVariables>
    <globalVariables>Phi</globalVariables>
    <globalVariables>Q_a</globalVariables>
    <globalVariables>Q_b</globalVariables>
    <globalVariables>RMSprop_epsilon</globalVariables>
    <globalVariables>RMSprop_eta</globalVariables>
    <globalVariables>RMSprop_gamma</globalVariables>
    <globalVariables>Red_Rate</globalVariables>
    <globalVariables>Time_Look</globalVariables>
    <globalVariables>Tz_lim_elarm</globalVariables>
    <globalVariables>Tz_lim_sharm</globalVariables>
    <globalVariables>Tz_lim_wrarm</globalVariables>
    <globalVariables>a</globalVariables>
    <globalVariables>a1</globalVariables>
    <globalVariables>a2</globalVariables>
    <globalVariables>a3</globalVariables>
    <globalVariables>adadelta_epsilon</globalVariables>
    <globalVariables>adadelta_gamma</globalVariables>
    <globalVariables>adagrad_epsilon</globalVariables>
    <globalVariables>adagrad_eta</globalVariables>
    <globalVariables>adam_beta_1</globalVariables>
    <globalVariables>adam_beta_2</globalVariables>
    <globalVariables>adam_epsilon</globalVariables>
    <globalVariables>adam_eta</globalVariables>
    <globalVariables>adamax_beta_1</globalVariables>
    <globalVariables>adamax_beta_2</globalVariables>
    <globalVariables>adamax_eta</globalVariables>
    <globalVariables>b0</globalVariables>
    <globalVariables>b1</globalVariables>
    <globalVariables>b2</globalVariables>
    <globalVariables>b3</globalVariables>
    <globalVariables>baseRate</globalVariables>
    <globalVariables>batch_eta</globalVariables>
    <globalVariables>drop_states_ARM</globalVariables>
    <globalVariables>drop_states_BLACK</globalVariables>
    <globalVariables>drop_states_BLUE</globalVariables>
    <globalVariables>drop_states_RED</globalVariables>
    <globalVariables>end_time_black</globalVariables>
    <globalVariables>end_time_blue</globalVariables>
    <globalVariables>home_states_BLACK</globalVariables>
    <globalVariables>home_states_BLUE</globalVariables>
    <globalVariables>home_states_RED</globalVariables>
    <globalVariables>init_states_BLACK</globalVariables>
    <globalVariables>init_states_BLUE</globalVariables>
    <globalVariables>init_states_RED</globalVariables>
    <globalVariables>k</globalVariables>
    <globalVariables>k_1_0</globalVariables>
    <globalVariables>k_1_t_0</globalVariables>
    <globalVariables>k_2_0</globalVariables>
    <globalVariables>k_2_t_0</globalVariables>
    <globalVariables>ka</globalVariables>
    <globalVariables>kr</globalVariables>
    <globalVariables>lambda1</globalVariables>
    <globalVariables>lambda12</globalVariables>
    <globalVariables>lambda12_t</globalVariables>
    <globalVariables>lambda1_t</globalVariables>
    <globalVariables>lambda2</globalVariables>
    <globalVariables>lambda2_t</globalVariables>
    <globalVariables>mBLACK</globalVariables>
    <globalVariables>mBLUE</globalVariables>
    <globalVariables>mDIST</globalVariables>
    <globalVariables>mEE</globalVariables>
    <globalVariables>mPROX</globalVariables>
    <globalVariables>mRED</globalVariables>
    <globalVariables>momentum_eta</globalVariables>
    <globalVariables>momentum_gamma</globalVariables>
    <globalVariables>nesterov_eta</globalVariables>
    <globalVariables>nesterov_gamma</globalVariables>
    <globalVariables>noise_variance_BLACK</globalVariables>
    <globalVariables>noise_variance_BLUE</globalVariables>
    <globalVariables>noise_variance_RED</globalVariables>
    <globalVariables>p</globalVariables>
    <globalVariables>p_t</globalVariables>
    <globalVariables>platformSelection</globalVariables>
    <globalVariables>psi</globalVariables>
    <globalVariables>r_hold</globalVariables>
    <globalVariables>r_off</globalVariables>
    <globalVariables>shape</globalVariables>
    <globalVariables>sigma</globalVariables>
    <globalVariables>simMode</globalVariables>
    <globalVariables>thruster_count_threshold</globalVariables>
    <globalVariables>thruster_dist2CG_BLACK</globalVariables>
    <globalVariables>thruster_dist2CG_BLUE</globalVariables>
    <globalVariables>thruster_dist2CG_RED</globalVariables>
    <globalVariables>tsim</globalVariables>
    <globalVariables>xLength</globalVariables>
    <globalVariables>yLength</globalVariables>
    <hasBlockWithPeriodicDiscreteSampleTime>true</hasBlockWithPeriodicDiscreteSampleTime>
    <hasBwsAccessed>true</hasBwsAccessed>
    <hasBwsAccessedByAnyModel>true</hasBwsAccessedByAnyModel>
    <hasContinuousSampleTime>true</hasContinuousSampleTime>
    <hasNonVirtualConstantTs>true</hasNonVirtualConstantTs>
    <hasNoncontSigFeedingDerivPorts>true</hasNoncontSigFeedingDerivPorts>
    <isBdInSimModeForSimCodegenVariants>false</isBdInSimModeForSimCodegenVariants>
    <loggingSaveFormat>2</loggingSaveFormat>
    <massMatrixNzMax>6</massMatrixNzMax>
    <maxFreqHz>-1.0</maxFreqHz>
    <needAbsoluteTimeDisallowInitPort>true</needAbsoluteTimeDisallowInitPort>
    <nonTunableVariables>a</nonTunableVariables>
    <nonTunableVariables>baseRate</nonTunableVariables>
    <nonTunableVariables>drop_states_ARM</nonTunableVariables>
    <nonTunableVariables>drop_states_RED</nonTunableVariables>
    <numCStateRecs>6</numCStateRecs>
    <numContinuousStates>6</numContinuousStates>
    <numDStateRecs>158</numDStateRecs>
    <numDataInputPorts>0</numDataInputPorts>
    <numLoggableCStateRecs>6</numLoggableCStateRecs>
    <numLoggableDStateRecs>158</numLoggableDStateRecs>
    <numLoggableJacobianDStates>207</numLoggableJacobianDStates>
    <removeResetFunc>true</removeResetFunc>
    <runtimeNonFcnCallRateInfos type="ModelRefInfoRepo.RateInfo">
      <compiled>true</compiled>
      <needAbsoluteTime>true</needAbsoluteTime>
      <period>0.0</period>
      <priority>40</priority>
      <rateIdx>0</rateIdx>
    </runtimeNonFcnCallRateInfos>
    <runtimeNonFcnCallRateInfos type="ModelRefInfoRepo.RateInfo">
      <compiled>true</compiled>
      <nonFcnCallPartitionName>Cont</nonFcnCallPartitionName>
      <period>.01</period>
      <priority>40</priority>
      <rateIdx>1</rateIdx>
    </runtimeNonFcnCallRateInfos>
    <sampleTimeInheritanceRule>2</sampleTimeInheritanceRule>
    <solverStatusFlags>323</solverStatusFlags>
    <timingAndTaskingRegistry>&lt;?xml version=&quot;1.0&quot;?&gt;
&lt;slexec_sto version=&quot;1.1&quot; packageUris=&quot;http://schema.mathworks.com/mf0/slexec_mm_sto/R2023a_202208151321&quot;&gt;
  &lt;sto.Registry type=&quot;sto.Registry&quot; uuid=&quot;a79ce83f-9469-4506-8fd4-764dc7138eff&quot;&gt;
    &lt;executionSpec&gt;Undetermined&lt;/executionSpec&gt;
    &lt;identifier&gt;APF_Path_Planning_2023a&lt;/identifier&gt;
    &lt;clockRegistry type=&quot;sto.ClockRegistry&quot; uuid=&quot;ae4041f4-179e-4350-80c4-48512f922240&quot;&gt;
      &lt;clocks type=&quot;sto.Timer&quot; uuid=&quot;084d6f27-b410-4152-989f-f88a34c441de&quot;&gt;
        &lt;clockTickConstraint&gt;PeriodicWithFixedResolution&lt;/clockTickConstraint&gt;
        &lt;computedFundamentalDiscretePeriod&gt;.01&lt;/computedFundamentalDiscretePeriod&gt;
        &lt;fastestDiscreteRate type=&quot;sto.ClassicPeriodicDiscreteRate&quot; uuid=&quot;8898ec31-8049-481a-a10c-dc977a58f7b5&quot;/&gt;
        &lt;isDefaultTimer&gt;true&lt;/isDefaultTimer&gt;
        &lt;resolution&gt;.01&lt;/resolution&gt;
        &lt;timeAdvanceMode&gt;FixedStep&lt;/timeAdvanceMode&gt;
        &lt;identifier&gt;APF_Path_Planning_2023a::defaultTimer&lt;/identifier&gt;
        &lt;rates type=&quot;sto.ContinuousRate&quot; uuid=&quot;3b0948ce-18ff-4104-a969-5505633597f5&quot;&gt;
          &lt;annotation&gt;Cont&lt;/annotation&gt;
          &lt;clockId&gt;APF_Path_Planning_2023a::defaultTimer&lt;/clockId&gt;
          &lt;description&gt;Continuous&lt;/description&gt;
          &lt;taskId&gt;_task0&lt;/taskId&gt;
          &lt;rateSpec type=&quot;sto.RateSpec&quot; uuid=&quot;e5cd8103-0124-4a00-9db1-4b74383a85ac&quot;/&gt;
        &lt;/rates&gt;
        &lt;rates type=&quot;sto.ClassicPeriodicDiscreteRate&quot; uuid=&quot;8898ec31-8049-481a-a10c-dc977a58f7b5&quot;&gt;
          &lt;annotation&gt;D1&lt;/annotation&gt;
          &lt;clockId&gt;APF_Path_Planning_2023a::defaultTimer&lt;/clockId&gt;
          &lt;colorIndex&gt;2&lt;/colorIndex&gt;
          &lt;description&gt;Discrete 1&lt;/description&gt;
          &lt;rateIdx&gt;1&lt;/rateIdx&gt;
          &lt;taskId&gt;_task0&lt;/taskId&gt;
          &lt;rateSpec type=&quot;sto.RateSpec&quot; uuid=&quot;770932f9-7a31-4cb0-b037-b5be8e6596d4&quot;&gt;
            &lt;period&gt;.01&lt;/period&gt;
            &lt;rateType&gt;ClassicPeriodicDiscrete&lt;/rateType&gt;
          &lt;/rateSpec&gt;
        &lt;/rates&gt;
        &lt;baseRate type=&quot;sto.ContinuousRate&quot; uuid=&quot;d70ca0e8-bc42-4b59-9b97-6fd7414db2e8&quot;&gt;
          &lt;annotation&gt;Cont&lt;/annotation&gt;
          &lt;clockId&gt;APF_Path_Planning_2023a::defaultTimer&lt;/clockId&gt;
          &lt;description&gt;Continuous&lt;/description&gt;
          &lt;taskId&gt;_task0&lt;/taskId&gt;
          &lt;rateSpec type=&quot;sto.RateSpec&quot; uuid=&quot;549efbe1-3682-4fc5-a9ad-6333030e2c9c&quot;/&gt;
        &lt;/baseRate&gt;
      &lt;/clocks&gt;
      &lt;clocks type=&quot;sto.Event&quot; uuid=&quot;a49b0aa1-c8f9-4b49-b9aa-ef90af3d599d&quot;&gt;
        &lt;eventType&gt;PARAMETER_CHANGE_EVENT&lt;/eventType&gt;
        &lt;cNum&gt;1&lt;/cNum&gt;
        &lt;clockType&gt;Event&lt;/clockType&gt;
        &lt;identifier&gt;ParameterChangeEvent&lt;/identifier&gt;
        &lt;rates type=&quot;sto.ModelWideEventRate&quot; uuid=&quot;51d4c7d2-c153-4411-9483-8f5b3e2cd742&quot;&gt;
          &lt;clockId&gt;ParameterChangeEvent&lt;/clockId&gt;
          &lt;rateIdx&gt;-1&lt;/rateIdx&gt;
          &lt;taskId&gt;ModelWideParameterChangeEvent&lt;/taskId&gt;
          &lt;useForExecution&gt;NotForExecution&lt;/useForExecution&gt;
          &lt;rateSpec type=&quot;sto.RateSpec&quot; uuid=&quot;05a85089-9dc8-43e0-90fb-45ef3be52f7a&quot;&gt;
            &lt;period&gt;inf&lt;/period&gt;
            &lt;rateType&gt;ModelWideParameterChangeEvent&lt;/rateType&gt;
          &lt;/rateSpec&gt;
        &lt;/rates&gt;
      &lt;/clocks&gt;
      &lt;timeAdvanceMode&gt;FixedStep&lt;/timeAdvanceMode&gt;
    &lt;/clockRegistry&gt;
    &lt;taskRegistry type=&quot;sto.TaskRegistry&quot; uuid=&quot;c1485f8a-7364-4ae4-b002-cc652aa447d3&quot;&gt;
      &lt;rootTaskHierarchyElements type=&quot;sto.Task&quot; uuid=&quot;406a3e6b-ce81-4ecf-a5a8-7482545bb2a1&quot;&gt;
        &lt;isExplicit&gt;true&lt;/isExplicit&gt;
        &lt;rates type=&quot;sto.ModelWideEventRate&quot; uuid=&quot;8a4545c0-9fc0-4665-97ca-246284cedf0f&quot;&gt;
          &lt;clockId&gt;ParameterChangeEvent&lt;/clockId&gt;
          &lt;rateIdx&gt;-1&lt;/rateIdx&gt;
          &lt;taskId&gt;ModelWideParameterChangeEvent&lt;/taskId&gt;
          &lt;useForExecution&gt;NotForExecution&lt;/useForExecution&gt;
          &lt;rateSpec type=&quot;sto.RateSpec&quot; uuid=&quot;81b888fe-f892-4088-b1ea-0d919e87ed6a&quot;&gt;
            &lt;period&gt;inf&lt;/period&gt;
            &lt;rateType&gt;ModelWideParameterChangeEvent&lt;/rateType&gt;
          &lt;/rateSpec&gt;
        &lt;/rates&gt;
        &lt;schedulingClockId&gt;ParameterChangeEvent&lt;/schedulingClockId&gt;
        &lt;timeKeeperClockId&gt;APF_Path_Planning_2023a::defaultTimer&lt;/timeKeeperClockId&gt;
        &lt;elementType&gt;Task&lt;/elementType&gt;
        &lt;identifier&gt;ModelWideParameterChangeEvent&lt;/identifier&gt;
        &lt;priority&gt;-1&lt;/priority&gt;
      &lt;/rootTaskHierarchyElements&gt;
      &lt;rootTaskHierarchyElements type=&quot;sto.Task&quot; uuid=&quot;cce72b4b-e4f2-42cb-b98d-f2eedc2dc787&quot;&gt;
        &lt;isExecutable&gt;true&lt;/isExecutable&gt;
        &lt;orderIndex&gt;1&lt;/orderIndex&gt;
        &lt;rates type=&quot;sto.ContinuousRate&quot; uuid=&quot;c50eb7d0-fd95-491b-b52d-474a22766126&quot;&gt;
          &lt;annotation&gt;Cont&lt;/annotation&gt;
          &lt;clockId&gt;APF_Path_Planning_2023a::defaultTimer&lt;/clockId&gt;
          &lt;description&gt;Continuous&lt;/description&gt;
          &lt;taskId&gt;_task0&lt;/taskId&gt;
          &lt;rateSpec type=&quot;sto.RateSpec&quot; uuid=&quot;8bcccd01-2724-41ff-a363-dc6f6d9259aa&quot;/&gt;
        &lt;/rates&gt;
        &lt;rates type=&quot;sto.ClassicPeriodicDiscreteRate&quot; uuid=&quot;f71761f5-b693-49aa-a86c-6cf08b5cca53&quot;&gt;
          &lt;annotation&gt;D1&lt;/annotation&gt;
          &lt;clockId&gt;APF_Path_Planning_2023a::defaultTimer&lt;/clockId&gt;
          &lt;colorIndex&gt;2&lt;/colorIndex&gt;
          &lt;description&gt;Discrete 1&lt;/description&gt;
          &lt;rateIdx&gt;1&lt;/rateIdx&gt;
          &lt;taskId&gt;_task0&lt;/taskId&gt;
          &lt;rateSpec type=&quot;sto.RateSpec&quot; uuid=&quot;18213197-8ab7-4725-9502-0f9c885e2d2c&quot;&gt;
            &lt;period&gt;.01&lt;/period&gt;
            &lt;rateType&gt;ClassicPeriodicDiscrete&lt;/rateType&gt;
          &lt;/rateSpec&gt;
        &lt;/rates&gt;
        &lt;schedulingClockId&gt;APF_Path_Planning_2023a::defaultTimer&lt;/schedulingClockId&gt;
        &lt;timeKeeperClockId&gt;APF_Path_Planning_2023a::defaultTimer&lt;/timeKeeperClockId&gt;
        &lt;elementType&gt;Task&lt;/elementType&gt;
        &lt;identifier&gt;_task0&lt;/identifier&gt;
        &lt;priority&gt;40&lt;/priority&gt;
      &lt;/rootTaskHierarchyElements&gt;
      &lt;taskDependencyGraph type=&quot;sto.SerializedTaskConnectionList&quot; uuid=&quot;a5787f6e-2829-4fab-aa22-86d4a93071ed&quot;&gt;
        &lt;clockIdentifier&gt;APF_Path_Planning_2023a::defaultTimer&lt;/clockIdentifier&gt;
        &lt;taskIdentifier&gt;_task0&lt;/taskIdentifier&gt;
      &lt;/taskDependencyGraph&gt;
      &lt;taskDependencyGraph type=&quot;sto.SerializedTaskConnectionList&quot; uuid=&quot;eae585bb-1e0f-416f-9e58-560d67753dbf&quot;&gt;
        &lt;clockIdentifier&gt;ParameterChangeEvent&lt;/clockIdentifier&gt;
        &lt;taskIdentifier&gt;ModelWideParameterChangeEvent&lt;/taskIdentifier&gt;
      &lt;/taskDependencyGraph&gt;
      &lt;taskPriorityDirection&gt;HighNumberLast&lt;/taskPriorityDirection&gt;
    &lt;/taskRegistry&gt;
  &lt;/sto.Registry&gt;
&lt;/slexec_sto&gt;</timingAndTaskingRegistry>
    <zeroInternalMemoryAtStartupUnchecked>true</zeroInternalMemoryAtStartupUnchecked>
    <FMUBlockMap type="ModelRefInfoRepo.FMUBlockInfo" uuid="329e6ead-1b1f-41c0-a811-ae561e0034f9"/>
    <codeGenInfo type="ModelRefInfoRepo.CodeGenInformation" uuid="d1b214af-d160-42c1-8783-90b43f6e36ed"/>
    <compiledVariantInfos type="ModelRefInfoRepo.CompiledVariantInfoMap" uuid="c74057e5-b40d-423c-8a22-fb3a039da6b3"/>
    <configSettingsForConsistencyChecks type="ModelRefInfoRepo.ConfigSettingsForConsistencyChecks" uuid="00d2e3c0-6a54-4883-bf98-254fe6e8c373">
      <consistentOutportInitialization>true</consistentOutportInitialization>
      <fixedStepSize>.01</fixedStepSize>
      <frameDiagnosticSetting>2</frameDiagnosticSetting>
      <hasHybridSampleTime>true</hasHybridSampleTime>
      <optimizedInitCode>true</optimizedInitCode>
      <signalLoggingSaveFormat>2</signalLoggingSaveFormat>
      <simSIMDOptimization>1</simSIMDOptimization>
      <solverName>ode4</solverName>
      <solverType>SOLVER_TYPE_FIXEDSTEP</solverType>
      <hardwareSettings type="ModelRefInfoRepo.HardwareSettings" uuid="fef8d13b-14a3-475c-866e-627776df2d3a">
        <prodBitPerChar>8</prodBitPerChar>
        <prodBitPerDouble>64</prodBitPerDouble>
        <prodBitPerFloat>32</prodBitPerFloat>
        <prodBitPerInt>32</prodBitPerInt>
        <prodBitPerLong>64</prodBitPerLong>
        <prodBitPerLongLong>64</prodBitPerLongLong>
        <prodBitPerPointer>64</prodBitPerPointer>
        <prodBitPerPtrDiffT>64</prodBitPerPtrDiffT>
        <prodBitPerShort>16</prodBitPerShort>
        <prodBitPerSizeT>64</prodBitPerSizeT>
        <prodEndianess>1</prodEndianess>
        <prodLargestAtomicFloat>1</prodLargestAtomicFloat>
        <prodLargestAtomicInteger>4</prodLargestAtomicInteger>
        <prodLongLongMode>true</prodLongLongMode>
        <prodShiftRight>true</prodShiftRight>
        <prodWordSize>64</prodWordSize>
      </hardwareSettings>
    </configSettingsForConsistencyChecks>
    <controllableInputRatesMap type="ModelRefInfoRepo.VarTsUIDMap" uuid="9548efed-62d9-4e84-90a3-bf89fbc617fb"/>
    <controllableOutputRatesMap type="ModelRefInfoRepo.VarTsUIDMap" uuid="7b6db15e-7abe-40ad-ab32-203f8c241ac3"/>
    <dataPortGroup type="ModelRefInfoRepo.DataPortGroup" uuid="136ae0fb-da9f-48c5-9f9b-a91d579c121d"/>
    <expFcnUnconnectedDataPortGroup type="ModelRefInfoRepo.DataPortGroup" uuid="f2333468-cadc-402c-aeb2-e068771be0c0"/>
    <interfaceParameterInfo type="ModelRefInfoRepo.InterfaceParameterInfo" uuid="b6c3d424-d7e1-4b70-ba8e-a00e7dd1a8b1">
      <globalVariables type="ModelRefInfoRepo.BuiltinParameter" uuid="f6490d58-9a07-4984-b4d7-c131605d5737">
        <dimensions>1</dimensions>
        <dimensions>1</dimensions>
        <isUsed>true</isUsed>
        <netSVCE>true</netSVCE>
        <numDimensions>2</numDimensions>
        <parameterName>Att_Mode</parameterName>
      </globalVariables>
      <globalVariables type="ModelRefInfoRepo.BuiltinParameter" uuid="691fa8fd-0744-4ab8-9c63-be1da4d5d37a">
        <dimensions>1</dimensions>
        <dimensions>3</dimensions>
        <isUsed>true</isUsed>
        <netSVCE>true</netSVCE>
        <numDimensions>2</numDimensions>
        <parameterName>BLACK_end</parameterName>
      </globalVariables>
      <globalVariables type="ModelRefInfoRepo.BuiltinParameter" uuid="8277834c-d5a5-4151-8d68-50e81eb1b641">
        <dimensions>1</dimensions>
        <dimensions>6</dimensions>
        <isUsed>true</isUsed>
        <netSVCE>true</netSVCE>
        <numDimensions>2</numDimensions>
        <parameterName>BLACK_ini</parameterName>
      </globalVariables>
      <globalVariables type="ModelRefInfoRepo.BuiltinParameter" uuid="253b1d6b-6c4a-4d93-970b-7feb795400b2">
        <dimensions>1</dimensions>
        <dimensions>3</dimensions>
        <isUsed>true</isUsed>
        <netSVCE>true</netSVCE>
        <numDimensions>2</numDimensions>
        <parameterName>BLUE_end</parameterName>
      </globalVariables>
      <globalVariables type="ModelRefInfoRepo.BuiltinParameter" uuid="69196a38-dbd6-421b-b7f7-0b55fedfc4a8">
        <dimensions>1</dimensions>
        <dimensions>6</dimensions>
        <isUsed>true</isUsed>
        <netSVCE>true</netSVCE>
        <numDimensions>2</numDimensions>
        <parameterName>BLUE_ini</parameterName>
      </globalVariables>
      <globalVariables type="ModelRefInfoRepo.BuiltinParameter" uuid="ae32ac4e-d410-44b8-becf-cf915aa2e208">
        <dimensions>3</dimensions>
        <dimensions>3</dimensions>
        <isUsed>true</isUsed>
        <netSVCE>true</netSVCE>
        <numDimensions>2</numDimensions>
        <parameterName>Binv</parameterName>
      </globalVariables>
      <globalVariables type="ModelRefInfoRepo.BuiltinParameter" uuid="ff7a326e-f63f-4a09-a716-6fefdd398088">
        <dimensions>1</dimensions>
        <dimensions>1</dimensions>
        <isUsed>true</isUsed>
        <netSVCE>true</netSVCE>
        <numDimensions>2</numDimensions>
        <parameterName>F_Black_X_nominal</parameterName>
      </globalVariables>
      <globalVariables type="ModelRefInfoRepo.BuiltinParameter" uuid="4ede451a-9d7e-4a6b-b4f1-7e50b2d84275">
        <dimensions>1</dimensions>
        <dimensions>1</dimensions>
        <isUsed>true</isUsed>
        <netSVCE>true</netSVCE>
        <numDimensions>2</numDimensions>
        <parameterName>F_Black_Y_nominal</parameterName>
      </globalVariables>
      <globalVariables type="ModelRefInfoRepo.BuiltinParameter" uuid="bac999db-9039-4704-b516-03169842743a">
        <dimensions>1</dimensions>
        <dimensions>1</dimensions>
        <isUsed>true</isUsed>
        <netSVCE>true</netSVCE>
        <numDimensions>2</numDimensions>
        <parameterName>F_Blue_X_nominal</parameterName>
      </globalVariables>
      <globalVariables type="ModelRefInfoRepo.BuiltinParameter" uuid="e1f1bfc2-dcd2-46df-9087-694a7f09490c">
        <dimensions>1</dimensions>
        <dimensions>1</dimensions>
        <isUsed>true</isUsed>
        <netSVCE>true</netSVCE>
        <numDimensions>2</numDimensions>
        <parameterName>F_Blue_Y_nominal</parameterName>
      </globalVariables>
      <globalVariables type="ModelRefInfoRepo.BuiltinParameter" uuid="f0f58767-f688-4d76-b538-9668c8da35ad">
        <dimensions>1</dimensions>
        <dimensions>1</dimensions>
        <isUsed>true</isUsed>
        <netSVCE>true</netSVCE>
        <numDimensions>2</numDimensions>
        <parameterName>F_red_X_nominal</parameterName>
      </globalVariables>
      <globalVariables type="ModelRefInfoRepo.BuiltinParameter" uuid="cddd3aa2-2ee7-476e-a5f4-2379c27ecac8">
        <dimensions>1</dimensions>
        <dimensions>1</dimensions>
        <isUsed>true</isUsed>
        <netSVCE>true</netSVCE>
        <numDimensions>2</numDimensions>
        <parameterName>F_red_Y_nominal</parameterName>
      </globalVariables>
      <globalVariables type="ModelRefInfoRepo.BuiltinParameter" uuid="ec0eccdc-65e1-467f-a6c2-5a1f724e6958">
        <dimensions>8</dimensions>
        <dimensions>1</dimensions>
        <isUsed>true</isUsed>
        <netSVCE>true</netSVCE>
        <numDimensions>2</numDimensions>
        <parameterName>F_thrusters_BLACK</parameterName>
      </globalVariables>
      <globalVariables type="ModelRefInfoRepo.BuiltinParameter" uuid="0e195df9-7f85-4ee8-882e-13a5c12d6177">
        <dimensions>8</dimensions>
        <dimensions>1</dimensions>
        <isUsed>true</isUsed>
        <netSVCE>true</netSVCE>
        <numDimensions>2</numDimensions>
        <parameterName>F_thrusters_BLUE</parameterName>
      </globalVariables>
      <globalVariables type="ModelRefInfoRepo.BuiltinParameter" uuid="f4297fc4-a132-45eb-87a7-ede85e801971">
        <dimensions>8</dimensions>
        <dimensions>1</dimensions>
        <isUsed>true</isUsed>
        <netSVCE>true</netSVCE>
        <numDimensions>2</numDimensions>
        <parameterName>F_thrusters_RED</parameterName>
      </globalVariables>
      <globalVariables type="ModelRefInfoRepo.BuiltinParameter" uuid="9468d44c-86ba-469b-8642-242faec36283">
        <dimensions>1</dimensions>
        <dimensions>1</dimensions>
        <isUsed>true</isUsed>
        <netSVCE>true</netSVCE>
        <numDimensions>2</numDimensions>
        <parameterName>Gamma1_el</parameterName>
      </globalVariables>
      <globalVariables type="ModelRefInfoRepo.BuiltinParameter" uuid="16bdb3f9-6e97-45bf-a7f8-4a0031d08a14">
        <dimensions>1</dimensions>
        <dimensions>1</dimensions>
        <isUsed>true</isUsed>
        <netSVCE>true</netSVCE>
        <numDimensions>2</numDimensions>
        <parameterName>Gamma1_sh</parameterName>
      </globalVariables>
      <globalVariables type="ModelRefInfoRepo.BuiltinParameter" uuid="7d022d32-8a96-433b-b5f5-118e5ed89ae8">
        <dimensions>1</dimensions>
        <dimensions>1</dimensions>
        <isUsed>true</isUsed>
        <netSVCE>true</netSVCE>
        <numDimensions>2</numDimensions>
        <parameterName>Gamma1_wr</parameterName>
      </globalVariables>
      <globalVariables type="ModelRefInfoRepo.BuiltinParameter" uuid="8cadb0a9-4253-4b1e-8ce0-08363c558bd0">
        <dimensions>1</dimensions>
        <dimensions>1</dimensions>
        <isUsed>true</isUsed>
        <netSVCE>true</netSVCE>
        <numDimensions>2</numDimensions>
        <parameterName>Gamma2_el</parameterName>
      </globalVariables>
      <globalVariables type="ModelRefInfoRepo.BuiltinParameter" uuid="4335bfcd-ce35-4730-aca2-b0ccc490397c">
        <dimensions>1</dimensions>
        <dimensions>1</dimensions>
        <isUsed>true</isUsed>
        <netSVCE>true</netSVCE>
        <numDimensions>2</numDimensions>
        <parameterName>Gamma2_sh</parameterName>
      </globalVariables>
      <globalVariables type="ModelRefInfoRepo.BuiltinParameter" uuid="314afd6f-78f5-4e77-a236-9d1275317763">
        <dimensions>1</dimensions>
        <dimensions>1</dimensions>
        <isUsed>true</isUsed>
        <netSVCE>true</netSVCE>
        <numDimensions>2</numDimensions>
        <parameterName>Gamma2_wr</parameterName>
      </globalVariables>
      <globalVariables type="ModelRefInfoRepo.BuiltinParameter" uuid="9b26a1c1-ba6c-4adb-a42f-77d08f3fcbc6">
        <dimensions>1</dimensions>
        <dimensions>1</dimensions>
        <isUsed>true</isUsed>
        <netSVCE>true</netSVCE>
        <numDimensions>2</numDimensions>
        <parameterName>Gamma3_el</parameterName>
      </globalVariables>
      <globalVariables type="ModelRefInfoRepo.BuiltinParameter" uuid="210444a6-179b-4eb7-80da-374429fcf082">
        <dimensions>1</dimensions>
        <dimensions>1</dimensions>
        <isUsed>true</isUsed>
        <netSVCE>true</netSVCE>
        <numDimensions>2</numDimensions>
        <parameterName>Gamma3_sh</parameterName>
      </globalVariables>
      <globalVariables type="ModelRefInfoRepo.BuiltinParameter" uuid="6f79f32a-0e05-4d16-90e1-9c53915248d3">
        <dimensions>1</dimensions>
        <dimensions>1</dimensions>
        <isUsed>true</isUsed>
        <netSVCE>true</netSVCE>
        <numDimensions>2</numDimensions>
        <parameterName>Gamma3_wr</parameterName>
      </globalVariables>
      <globalVariables type="ModelRefInfoRepo.BuiltinParameter" uuid="bfe0cb07-1832-417c-bd26-186e9c3273a7">
        <dimensions>1</dimensions>
        <dimensions>1</dimensions>
        <isUsed>true</isUsed>
        <netSVCE>true</netSVCE>
        <numDimensions>2</numDimensions>
        <parameterName>Gamma4_el</parameterName>
      </globalVariables>
      <globalVariables type="ModelRefInfoRepo.BuiltinParameter" uuid="d9615d8d-6030-4e21-896c-02b63262a27d">
        <dimensions>1</dimensions>
        <dimensions>1</dimensions>
        <isUsed>true</isUsed>
        <netSVCE>true</netSVCE>
        <numDimensions>2</numDimensions>
        <parameterName>Gamma4_sh</parameterName>
      </globalVariables>
      <globalVariables type="ModelRefInfoRepo.BuiltinParameter" uuid="dce6661c-1bb7-451a-8b9e-bece9cfdb59c">
        <dimensions>1</dimensions>
        <dimensions>1</dimensions>
        <isUsed>true</isUsed>
        <netSVCE>true</netSVCE>
        <numDimensions>2</numDimensions>
        <parameterName>Gamma4_wr</parameterName>
      </globalVariables>
      <globalVariables type="ModelRefInfoRepo.BuiltinParameter" uuid="2baf2d5c-0c91-450d-93ac-979e1b63e909">
        <dimensions>1</dimensions>
        <dimensions>1</dimensions>
        <isUsed>true</isUsed>
        <netSVCE>true</netSVCE>
        <numDimensions>2</numDimensions>
        <parameterName>Gamma5_el</parameterName>
      </globalVariables>
      <globalVariables type="ModelRefInfoRepo.BuiltinParameter" uuid="9eeaf5b3-28e9-4b37-a789-bc56af5de037">
        <dimensions>1</dimensions>
        <dimensions>1</dimensions>
        <isUsed>true</isUsed>
        <netSVCE>true</netSVCE>
        <numDimensions>2</numDimensions>
        <parameterName>Gamma5_sh</parameterName>
      </globalVariables>
      <globalVariables type="ModelRefInfoRepo.BuiltinParameter" uuid="cf5343f7-d99f-42e3-bd4e-086cefe8a0a0">
        <dimensions>1</dimensions>
        <dimensions>1</dimensions>
        <isUsed>true</isUsed>
        <netSVCE>true</netSVCE>
        <numDimensions>2</numDimensions>
        <parameterName>Gamma5_wr</parameterName>
      </globalVariables>
      <globalVariables type="ModelRefInfoRepo.BuiltinParameter" uuid="a65179bf-a512-46d5-8453-91571cba9e48">
        <dimensions>1</dimensions>
        <dimensions>1</dimensions>
        <isUsed>true</isUsed>
        <netSVCE>true</netSVCE>
        <numDimensions>2</numDimensions>
        <parameterName>Gamma6_el</parameterName>
      </globalVariables>
      <globalVariables type="ModelRefInfoRepo.BuiltinParameter" uuid="a3e7224e-5d11-4ed4-be4e-44ae64f4550c">
        <dimensions>1</dimensions>
        <dimensions>1</dimensions>
        <isUsed>true</isUsed>
        <netSVCE>true</netSVCE>
        <numDimensions>2</numDimensions>
        <parameterName>Gamma6_sh</parameterName>
      </globalVariables>
      <globalVariables type="ModelRefInfoRepo.BuiltinParameter" uuid="d41091d6-038c-411a-8af9-ad761084cd6e">
        <dimensions>1</dimensions>
        <dimensions>1</dimensions>
        <isUsed>true</isUsed>
        <netSVCE>true</netSVCE>
        <numDimensions>2</numDimensions>
        <parameterName>Gamma6_wr</parameterName>
      </globalVariables>
      <globalVariables type="ModelRefInfoRepo.BuiltinParameter" uuid="8a1a8016-cd5d-4c92-a867-6173a97d4ac0">
        <dimensions>1</dimensions>
        <dimensions>1</dimensions>
        <isUsed>true</isUsed>
        <netSVCE>true</netSVCE>
        <numDimensions>2</numDimensions>
        <parameterName>Hz</parameterName>
      </globalVariables>
      <globalVariables type="ModelRefInfoRepo.BuiltinParameter" uuid="cf2c5dcc-2c76-4364-8487-69dae3b3cd78">
        <dimensions>1</dimensions>
        <dimensions>1</dimensions>
        <isUsed>true</isUsed>
        <netSVCE>true</netSVCE>
        <numDimensions>2</numDimensions>
        <parameterName>IBLACK</parameterName>
      </globalVariables>
      <globalVariables type="ModelRefInfoRepo.BuiltinParameter" uuid="8f8e5603-7761-48ca-8cc5-f7353f781623">
        <dimensions>1</dimensions>
        <dimensions>1</dimensions>
        <isUsed>true</isUsed>
        <netSVCE>true</netSVCE>
        <numDimensions>2</numDimensions>
        <parameterName>IBLUE</parameterName>
      </globalVariables>
      <globalVariables type="ModelRefInfoRepo.BuiltinParameter" uuid="da33b49c-1812-4905-ae13-3b5111333799">
        <dimensions>1</dimensions>
        <dimensions>1</dimensions>
        <isUsed>true</isUsed>
        <netSVCE>true</netSVCE>
        <numDimensions>2</numDimensions>
        <parameterName>IDIST</parameterName>
      </globalVariables>
      <globalVariables type="ModelRefInfoRepo.BuiltinParameter" uuid="bed6f5eb-4ef6-4a85-9ddf-932ee571f57b">
        <dimensions>1</dimensions>
        <dimensions>1</dimensions>
        <isUsed>true</isUsed>
        <netSVCE>true</netSVCE>
        <numDimensions>2</numDimensions>
        <parameterName>IEE</parameterName>
      </globalVariables>
      <globalVariables type="ModelRefInfoRepo.BuiltinParameter" uuid="4eb1b9bb-80bd-41a1-a5b8-d720b01828ff">
        <dimensions>1</dimensions>
        <dimensions>1</dimensions>
        <isUsed>true</isUsed>
        <netSVCE>true</netSVCE>
        <numDimensions>2</numDimensions>
        <parameterName>IPROX</parameterName>
      </globalVariables>
      <globalVariables type="ModelRefInfoRepo.BuiltinParameter" uuid="5f0e9fb0-81a0-4b94-800d-fb31605510d8">
        <dimensions>1</dimensions>
        <dimensions>1</dimensions>
        <isUsed>true</isUsed>
        <netSVCE>true</netSVCE>
        <numDimensions>2</numDimensions>
        <parameterName>IRED</parameterName>
      </globalVariables>
      <globalVariables type="ModelRefInfoRepo.BuiltinParameter" uuid="bba825ee-7e95-45df-97dc-f650b6aef348">
        <dimensions>3</dimensions>
        <dimensions>3</dimensions>
        <isUsed>true</isUsed>
        <netSVCE>true</netSVCE>
        <numDimensions>2</numDimensions>
        <parameterName>K_a</parameterName>
      </globalVariables>
      <globalVariables type="ModelRefInfoRepo.BuiltinParameter" uuid="4b4327c4-b2ec-472b-87e3-563778445e78">
        <dimensions>1</dimensions>
        <dimensions>1</dimensions>
        <isUsed>true</isUsed>
        <netSVCE>true</netSVCE>
        <numDimensions>2</numDimensions>
        <parameterName>Kd_elarm</parameterName>
      </globalVariables>
      <globalVariables type="ModelRefInfoRepo.BuiltinParameter" uuid="c6265ad4-d24e-41e4-ab6b-3c435a7281ef">
        <dimensions>1</dimensions>
        <dimensions>1</dimensions>
        <isUsed>true</isUsed>
        <netSVCE>true</netSVCE>
        <numDimensions>2</numDimensions>
        <parameterName>Kd_sharm</parameterName>
      </globalVariables>
      <globalVariables type="ModelRefInfoRepo.BuiltinParameter" uuid="252109f6-bab5-4969-bacb-302299a11104">
        <dimensions>1</dimensions>
        <dimensions>1</dimensions>
        <isUsed>true</isUsed>
        <netSVCE>true</netSVCE>
        <numDimensions>2</numDimensions>
        <parameterName>Kd_tb</parameterName>
      </globalVariables>
      <globalVariables type="ModelRefInfoRepo.BuiltinParameter" uuid="14fbc5bd-549d-4dfb-8668-c2290a7cdc62">
        <dimensions>1</dimensions>
        <dimensions>1</dimensions>
        <isUsed>true</isUsed>
        <netSVCE>true</netSVCE>
        <numDimensions>2</numDimensions>
        <parameterName>Kd_tblue</parameterName>
      </globalVariables>
      <globalVariables type="ModelRefInfoRepo.BuiltinParameter" uuid="25ab0a41-90f6-4b37-8ebb-3c8d039343d9">
        <dimensions>1</dimensions>
        <dimensions>1</dimensions>
        <isUsed>true</isUsed>
        <netSVCE>true</netSVCE>
        <numDimensions>2</numDimensions>
        <parameterName>Kd_tr</parameterName>
      </globalVariables>
      <globalVariables type="ModelRefInfoRepo.BuiltinParameter" uuid="635c30f0-06a9-4a14-969d-1d07065d0a7c">
        <dimensions>1</dimensions>
        <dimensions>1</dimensions>
        <isUsed>true</isUsed>
        <netSVCE>true</netSVCE>
        <numDimensions>2</numDimensions>
        <parameterName>Kd_wrarm</parameterName>
      </globalVariables>
      <globalVariables type="ModelRefInfoRepo.BuiltinParameter" uuid="a9a85104-cda5-4950-9e8f-b1b8c1aa2fe5">
        <dimensions>1</dimensions>
        <dimensions>1</dimensions>
        <isUsed>true</isUsed>
        <netSVCE>true</netSVCE>
        <numDimensions>2</numDimensions>
        <parameterName>Kd_xb</parameterName>
      </globalVariables>
      <globalVariables type="ModelRefInfoRepo.BuiltinParameter" uuid="eeeaa8ec-8f1c-4af6-85e7-b72808359f8f">
        <dimensions>1</dimensions>
        <dimensions>1</dimensions>
        <isUsed>true</isUsed>
        <netSVCE>true</netSVCE>
        <numDimensions>2</numDimensions>
        <parameterName>Kd_xblue</parameterName>
      </globalVariables>
      <globalVariables type="ModelRefInfoRepo.BuiltinParameter" uuid="f835b5b8-dfd7-4738-baab-4969fe91e290">
        <dimensions>1</dimensions>
        <dimensions>1</dimensions>
        <isUsed>true</isUsed>
        <netSVCE>true</netSVCE>
        <numDimensions>2</numDimensions>
        <parameterName>Kd_xr</parameterName>
      </globalVariables>
      <globalVariables type="ModelRefInfoRepo.BuiltinParameter" uuid="1c0e16ed-62bf-4f6d-a58c-78e280f1bbd3">
        <dimensions>1</dimensions>
        <dimensions>1</dimensions>
        <isUsed>true</isUsed>
        <netSVCE>true</netSVCE>
        <numDimensions>2</numDimensions>
        <parameterName>Kd_yb</parameterName>
      </globalVariables>
      <globalVariables type="ModelRefInfoRepo.BuiltinParameter" uuid="9080ce59-39ed-4510-b6f5-711419b7f471">
        <dimensions>1</dimensions>
        <dimensions>1</dimensions>
        <isUsed>true</isUsed>
        <netSVCE>true</netSVCE>
        <numDimensions>2</numDimensions>
        <parameterName>Kd_yblue</parameterName>
      </globalVariables>
      <globalVariables type="ModelRefInfoRepo.BuiltinParameter" uuid="e40153f4-70d9-47db-80d7-a0afb0282cdc">
        <dimensions>1</dimensions>
        <dimensions>1</dimensions>
        <isUsed>true</isUsed>
        <netSVCE>true</netSVCE>
        <numDimensions>2</numDimensions>
        <parameterName>Kd_yr</parameterName>
      </globalVariables>
      <globalVariables type="ModelRefInfoRepo.BuiltinParameter" uuid="3703fb4d-3e0a-4a52-869a-3bfa19203146">
        <dimensions>1</dimensions>
        <dimensions>1</dimensions>
        <isUsed>true</isUsed>
        <netSVCE>true</netSVCE>
        <numDimensions>2</numDimensions>
        <parameterName>Kp_elarm</parameterName>
      </globalVariables>
      <globalVariables type="ModelRefInfoRepo.BuiltinParameter" uuid="09417417-ec78-43e4-b8a6-d2f8c72f9783">
        <dimensions>1</dimensions>
        <dimensions>1</dimensions>
        <isUsed>true</isUsed>
        <netSVCE>true</netSVCE>
        <numDimensions>2</numDimensions>
        <parameterName>Kp_sharm</parameterName>
      </globalVariables>
      <globalVariables type="ModelRefInfoRepo.BuiltinParameter" uuid="3488f8b0-4d63-4905-b063-0475ad604dec">
        <dimensions>1</dimensions>
        <dimensions>1</dimensions>
        <isUsed>true</isUsed>
        <netSVCE>true</netSVCE>
        <numDimensions>2</numDimensions>
        <parameterName>Kp_tb</parameterName>
      </globalVariables>
      <globalVariables type="ModelRefInfoRepo.BuiltinParameter" uuid="2e14a079-bb60-4449-9523-56dc50c91df8">
        <dimensions>1</dimensions>
        <dimensions>1</dimensions>
        <isUsed>true</isUsed>
        <netSVCE>true</netSVCE>
        <numDimensions>2</numDimensions>
        <parameterName>Kp_tblue</parameterName>
      </globalVariables>
      <globalVariables type="ModelRefInfoRepo.BuiltinParameter" uuid="155886f9-03ab-4adf-b6b1-4a80fa6016d0">
        <dimensions>1</dimensions>
        <dimensions>1</dimensions>
        <isUsed>true</isUsed>
        <netSVCE>true</netSVCE>
        <numDimensions>2</numDimensions>
        <parameterName>Kp_tr</parameterName>
      </globalVariables>
      <globalVariables type="ModelRefInfoRepo.BuiltinParameter" uuid="3d2e721f-691f-4835-bb22-c045418512b0">
        <dimensions>1</dimensions>
        <dimensions>1</dimensions>
        <isUsed>true</isUsed>
        <netSVCE>true</netSVCE>
        <numDimensions>2</numDimensions>
        <parameterName>Kp_wrarm</parameterName>
      </globalVariables>
      <globalVariables type="ModelRefInfoRepo.BuiltinParameter" uuid="55668db9-6296-43a6-8131-eeb91a73fe48">
        <dimensions>1</dimensions>
        <dimensions>1</dimensions>
        <isUsed>true</isUsed>
        <netSVCE>true</netSVCE>
        <numDimensions>2</numDimensions>
        <parameterName>Kp_xb</parameterName>
      </globalVariables>
      <globalVariables type="ModelRefInfoRepo.BuiltinParameter" uuid="a848b89e-facd-4dbe-b949-5bfc1d15735f">
        <dimensions>1</dimensions>
        <dimensions>1</dimensions>
        <isUsed>true</isUsed>
        <netSVCE>true</netSVCE>
        <numDimensions>2</numDimensions>
        <parameterName>Kp_xblue</parameterName>
      </globalVariables>
      <globalVariables type="ModelRefInfoRepo.BuiltinParameter" uuid="279b3423-1712-4737-8604-3731bee83a4b">
        <dimensions>1</dimensions>
        <dimensions>1</dimensions>
        <isUsed>true</isUsed>
        <netSVCE>true</netSVCE>
        <numDimensions>2</numDimensions>
        <parameterName>Kp_xr</parameterName>
      </globalVariables>
      <globalVariables type="ModelRefInfoRepo.BuiltinParameter" uuid="b5df6c65-5cc0-46f1-ba95-c7915460ea69">
        <dimensions>1</dimensions>
        <dimensions>1</dimensions>
        <isUsed>true</isUsed>
        <netSVCE>true</netSVCE>
        <numDimensions>2</numDimensions>
        <parameterName>Kp_yb</parameterName>
      </globalVariables>
      <globalVariables type="ModelRefInfoRepo.BuiltinParameter" uuid="1dcde423-6ec0-4987-8658-90f5c5eff851">
        <dimensions>1</dimensions>
        <dimensions>1</dimensions>
        <isUsed>true</isUsed>
        <netSVCE>true</netSVCE>
        <numDimensions>2</numDimensions>
        <parameterName>Kp_yblue</parameterName>
      </globalVariables>
      <globalVariables type="ModelRefInfoRepo.BuiltinParameter" uuid="5e256051-06a9-4e2b-ad9c-0cf290ccb989">
        <dimensions>1</dimensions>
        <dimensions>1</dimensions>
        <isUsed>true</isUsed>
        <netSVCE>true</netSVCE>
        <numDimensions>2</numDimensions>
        <parameterName>Kp_yr</parameterName>
      </globalVariables>
      <globalVariables type="ModelRefInfoRepo.BuiltinParameter" uuid="80957885-a33c-4778-81bb-41861b278ab3">
        <dimensions>1</dimensions>
        <dimensions>1</dimensions>
        <isUsed>true</isUsed>
        <netSVCE>true</netSVCE>
        <numDimensions>2</numDimensions>
        <parameterName>Method</parameterName>
      </globalVariables>
      <globalVariables type="ModelRefInfoRepo.BuiltinParameter" uuid="8c788b82-1465-448f-872a-ed80cbd76fd0">
        <dimensions>3</dimensions>
        <dimensions>3</dimensions>
        <isUsed>true</isUsed>
        <netSVCE>true</netSVCE>
        <numDimensions>2</numDimensions>
        <parameterName>Nmat</parameterName>
      </globalVariables>
      <globalVariables type="ModelRefInfoRepo.BuiltinParameter" uuid="b56bae26-7a3e-4282-8de2-252c9568a452">
        <dimensions>1</dimensions>
        <dimensions>1</dimensions>
        <isUsed>true</isUsed>
        <netSVCE>true</netSVCE>
        <numDimensions>2</numDimensions>
        <parameterName>PWMFreq</parameterName>
      </globalVariables>
      <globalVariables type="ModelRefInfoRepo.BuiltinParameter" uuid="f6e245b1-b4f8-49ce-bbc8-a0a61d4b0e97">
        <dimensions>3</dimensions>
        <dimensions>3</dimensions>
        <isUsed>true</isUsed>
        <netSVCE>true</netSVCE>
        <numDimensions>2</numDimensions>
        <parameterName>P_b</parameterName>
      </globalVariables>
      <globalVariables type="ModelRefInfoRepo.BuiltinParameter" uuid="2ce12a0a-ec53-4643-ad77-ce372779933b">
        <dimensions>1</dimensions>
        <dimensions>1</dimensions>
        <isUsed>true</isUsed>
        <netSVCE>true</netSVCE>
        <numDimensions>2</numDimensions>
        <parameterName>Phase0_End</parameterName>
      </globalVariables>
      <globalVariables type="ModelRefInfoRepo.BuiltinParameter" uuid="67c94329-6089-47dd-8c06-9108df54350d">
        <dimensions>1</dimensions>
        <dimensions>1</dimensions>
        <isUsed>true</isUsed>
        <netSVCE>true</netSVCE>
        <numDimensions>2</numDimensions>
        <parameterName>Phase1_End</parameterName>
      </globalVariables>
      <globalVariables type="ModelRefInfoRepo.BuiltinParameter" uuid="f3788588-bdbb-4d71-8215-61d9cea0a1e7">
        <dimensions>1</dimensions>
        <dimensions>1</dimensions>
        <isUsed>true</isUsed>
        <netSVCE>true</netSVCE>
        <numDimensions>2</numDimensions>
        <parameterName>Phase2_End</parameterName>
      </globalVariables>
      <globalVariables type="ModelRefInfoRepo.BuiltinParameter" uuid="6a1ef42f-06ed-4c9b-a7b6-21ab2f88cc7a">
        <dimensions>1</dimensions>
        <dimensions>1</dimensions>
        <isUsed>true</isUsed>
        <netSVCE>true</netSVCE>
        <numDimensions>2</numDimensions>
        <parameterName>Phase3_End</parameterName>
      </globalVariables>
      <globalVariables type="ModelRefInfoRepo.BuiltinParameter" uuid="9a4bda90-0027-48ec-ac11-5e5a4be1037b">
        <dimensions>1</dimensions>
        <dimensions>1</dimensions>
        <isUsed>true</isUsed>
        <netSVCE>true</netSVCE>
        <numDimensions>2</numDimensions>
        <parameterName>Phase3_SubPhase1_End</parameterName>
      </globalVariables>
      <globalVariables type="ModelRefInfoRepo.BuiltinParameter" uuid="a569271a-c367-4d52-9fbc-1fa5f216b971">
        <dimensions>1</dimensions>
        <dimensions>1</dimensions>
        <isUsed>true</isUsed>
        <netSVCE>true</netSVCE>
        <numDimensions>2</numDimensions>
        <parameterName>Phase3_SubPhase2_End</parameterName>
      </globalVariables>
      <globalVariables type="ModelRefInfoRepo.BuiltinParameter" uuid="d68234bc-4843-4064-8038-6dba1fbf709a">
        <dimensions>1</dimensions>
        <dimensions>1</dimensions>
        <isUsed>true</isUsed>
        <netSVCE>true</netSVCE>
        <numDimensions>2</numDimensions>
        <parameterName>Phase3_SubPhase3_End</parameterName>
      </globalVariables>
      <globalVariables type="ModelRefInfoRepo.BuiltinParameter" uuid="6b47b551-9474-4f09-bde6-123b83731320">
        <dimensions>1</dimensions>
        <dimensions>1</dimensions>
        <isUsed>true</isUsed>
        <netSVCE>true</netSVCE>
        <numDimensions>2</numDimensions>
        <parameterName>Phase3_SubPhase4_End</parameterName>
      </globalVariables>
      <globalVariables type="ModelRefInfoRepo.BuiltinParameter" uuid="65183dac-ef6a-4b75-b8fc-34f746d38bf3">
        <dimensions>1</dimensions>
        <dimensions>1</dimensions>
        <isUsed>true</isUsed>
        <netSVCE>true</netSVCE>
        <numDimensions>2</numDimensions>
        <parameterName>Phase4_End</parameterName>
      </globalVariables>
      <globalVariables type="ModelRefInfoRepo.BuiltinParameter" uuid="fc0d71a6-76f3-4855-8fe4-92e9a7fe24a6">
        <dimensions>1</dimensions>
        <dimensions>1</dimensions>
        <isUsed>true</isUsed>
        <netSVCE>true</netSVCE>
        <numDimensions>2</numDimensions>
        <parameterName>Phase5_End</parameterName>
      </globalVariables>
      <globalVariables type="ModelRefInfoRepo.BuiltinParameter" uuid="b9ed7790-0b29-47d1-a874-3d434c4ea8e5">
        <dimensions>1</dimensions>
        <dimensions>1</dimensions>
        <isUsed>true</isUsed>
        <netSVCE>true</netSVCE>
        <numDimensions>2</numDimensions>
        <parameterName>Phi</parameterName>
      </globalVariables>
      <globalVariables type="ModelRefInfoRepo.BuiltinParameter" uuid="1b19ee70-4698-41f1-b652-9c6e7de37633">
        <dimensions>3</dimensions>
        <dimensions>3</dimensions>
        <isUsed>true</isUsed>
        <netSVCE>true</netSVCE>
        <numDimensions>2</numDimensions>
        <parameterName>Q_a</parameterName>
      </globalVariables>
      <globalVariables type="ModelRefInfoRepo.BuiltinParameter" uuid="51490c5d-e97c-4553-bd38-65ecaa0ed347">
        <dimensions>3</dimensions>
        <dimensions>3</dimensions>
        <isUsed>true</isUsed>
        <netSVCE>true</netSVCE>
        <numDimensions>2</numDimensions>
        <parameterName>Q_b</parameterName>
      </globalVariables>
      <globalVariables type="ModelRefInfoRepo.BuiltinParameter" uuid="c82d0b7f-5fec-409a-b617-d7f9f8d4872f">
        <dimensions>1</dimensions>
        <dimensions>1</dimensions>
        <isUsed>true</isUsed>
        <netSVCE>true</netSVCE>
        <numDimensions>2</numDimensions>
        <parameterName>RMSprop_epsilon</parameterName>
      </globalVariables>
      <globalVariables type="ModelRefInfoRepo.BuiltinParameter" uuid="c5fd30ca-3cdc-465f-89b7-1b1d73b0bae6">
        <dimensions>1</dimensions>
        <dimensions>1</dimensions>
        <isUsed>true</isUsed>
        <netSVCE>true</netSVCE>
        <numDimensions>2</numDimensions>
        <parameterName>RMSprop_eta</parameterName>
      </globalVariables>
      <globalVariables type="ModelRefInfoRepo.BuiltinParameter" uuid="ff666595-1427-4866-b8dd-731864cb652a">
        <dimensions>1</dimensions>
        <dimensions>1</dimensions>
        <isUsed>true</isUsed>
        <netSVCE>true</netSVCE>
        <numDimensions>2</numDimensions>
        <parameterName>RMSprop_gamma</parameterName>
      </globalVariables>
      <globalVariables type="ModelRefInfoRepo.BuiltinParameter" uuid="f1bd5877-a612-467a-8521-b198097b0a6c">
        <dimensions>1</dimensions>
        <dimensions>1</dimensions>
        <isUsed>true</isUsed>
        <netSVCE>true</netSVCE>
        <numDimensions>2</numDimensions>
        <parameterName>Red_Rate</parameterName>
      </globalVariables>
      <globalVariables type="ModelRefInfoRepo.BuiltinParameter" uuid="fa31d5bf-4f30-4a01-a491-a25c88d6fca9">
        <dimensions>1</dimensions>
        <dimensions>1</dimensions>
        <isUsed>true</isUsed>
        <netSVCE>true</netSVCE>
        <numDimensions>2</numDimensions>
        <parameterName>Time_Look</parameterName>
      </globalVariables>
      <globalVariables type="ModelRefInfoRepo.BuiltinParameter" uuid="31abf252-a38e-4de9-a9e6-eef780e21b95">
        <dimensions>1</dimensions>
        <dimensions>1</dimensions>
        <isUsed>true</isUsed>
        <netSVCE>true</netSVCE>
        <numDimensions>2</numDimensions>
        <parameterName>Tz_lim_elarm</parameterName>
      </globalVariables>
      <globalVariables type="ModelRefInfoRepo.BuiltinParameter" uuid="f55ae704-59a8-41bb-bbfe-858b1df61ed9">
        <dimensions>1</dimensions>
        <dimensions>1</dimensions>
        <isUsed>true</isUsed>
        <netSVCE>true</netSVCE>
        <numDimensions>2</numDimensions>
        <parameterName>Tz_lim_sharm</parameterName>
      </globalVariables>
      <globalVariables type="ModelRefInfoRepo.BuiltinParameter" uuid="a11342c7-7899-4deb-8894-c1d24446d986">
        <dimensions>1</dimensions>
        <dimensions>1</dimensions>
        <isUsed>true</isUsed>
        <netSVCE>true</netSVCE>
        <numDimensions>2</numDimensions>
        <parameterName>Tz_lim_wrarm</parameterName>
      </globalVariables>
      <globalVariables type="ModelRefInfoRepo.BuiltinParameter" uuid="f29b1e87-b369-4fd7-979f-181e7e58129e">
        <dimensions>1</dimensions>
        <dimensions>1</dimensions>
        <isUsed>true</isUsed>
        <netSVCE>true</netSVCE>
        <numDimensions>2</numDimensions>
        <parameterName>a1</parameterName>
      </globalVariables>
      <globalVariables type="ModelRefInfoRepo.BuiltinParameter" uuid="3165aebe-b9af-4d8c-83d2-75a6b964fbef">
        <dimensions>1</dimensions>
        <dimensions>1</dimensions>
        <isUsed>true</isUsed>
        <netSVCE>true</netSVCE>
        <numDimensions>2</numDimensions>
        <parameterName>a2</parameterName>
      </globalVariables>
      <globalVariables type="ModelRefInfoRepo.BuiltinParameter" uuid="14f8c848-bc6b-4ff8-b3cd-e6c03b3ea618">
        <dimensions>1</dimensions>
        <dimensions>1</dimensions>
        <isUsed>true</isUsed>
        <netSVCE>true</netSVCE>
        <numDimensions>2</numDimensions>
        <parameterName>a3</parameterName>
      </globalVariables>
      <globalVariables type="ModelRefInfoRepo.BuiltinParameter" uuid="67fc8eaa-b903-487b-b6d3-0594d263c829">
        <dimensions>1</dimensions>
        <dimensions>1</dimensions>
        <isUsed>true</isUsed>
        <netSVCE>true</netSVCE>
        <numDimensions>2</numDimensions>
        <parameterName>adadelta_epsilon</parameterName>
      </globalVariables>
      <globalVariables type="ModelRefInfoRepo.BuiltinParameter" uuid="367ac70d-68c8-4c8a-bda9-fff98d23b6e0">
        <dimensions>1</dimensions>
        <dimensions>1</dimensions>
        <isUsed>true</isUsed>
        <netSVCE>true</netSVCE>
        <numDimensions>2</numDimensions>
        <parameterName>adadelta_gamma</parameterName>
      </globalVariables>
      <globalVariables type="ModelRefInfoRepo.BuiltinParameter" uuid="176028e8-1723-4b64-8248-5842bbb41b1d">
        <dimensions>1</dimensions>
        <dimensions>1</dimensions>
        <isUsed>true</isUsed>
        <netSVCE>true</netSVCE>
        <numDimensions>2</numDimensions>
        <parameterName>adagrad_epsilon</parameterName>
      </globalVariables>
      <globalVariables type="ModelRefInfoRepo.BuiltinParameter" uuid="2530cddc-fe6d-4b50-96e4-5aece0a65763">
        <dimensions>1</dimensions>
        <dimensions>1</dimensions>
        <isUsed>true</isUsed>
        <netSVCE>true</netSVCE>
        <numDimensions>2</numDimensions>
        <parameterName>adagrad_eta</parameterName>
      </globalVariables>
      <globalVariables type="ModelRefInfoRepo.BuiltinParameter" uuid="e680f5a5-96ea-4574-a587-07140b82ce28">
        <dimensions>1</dimensions>
        <dimensions>1</dimensions>
        <isUsed>true</isUsed>
        <netSVCE>true</netSVCE>
        <numDimensions>2</numDimensions>
        <parameterName>adam_beta_1</parameterName>
      </globalVariables>
      <globalVariables type="ModelRefInfoRepo.BuiltinParameter" uuid="25f3ea36-076e-4804-b27e-7d225f9d8256">
        <dimensions>1</dimensions>
        <dimensions>1</dimensions>
        <isUsed>true</isUsed>
        <netSVCE>true</netSVCE>
        <numDimensions>2</numDimensions>
        <parameterName>adam_beta_2</parameterName>
      </globalVariables>
      <globalVariables type="ModelRefInfoRepo.BuiltinParameter" uuid="b84e09ac-bfb5-4b04-a2ca-2f77467440ff">
        <dimensions>1</dimensions>
        <dimensions>1</dimensions>
        <isUsed>true</isUsed>
        <netSVCE>true</netSVCE>
        <numDimensions>2</numDimensions>
        <parameterName>adam_epsilon</parameterName>
      </globalVariables>
      <globalVariables type="ModelRefInfoRepo.BuiltinParameter" uuid="c641f2e9-6600-4ca4-a094-34c9025240dc">
        <dimensions>1</dimensions>
        <dimensions>1</dimensions>
        <isUsed>true</isUsed>
        <netSVCE>true</netSVCE>
        <numDimensions>2</numDimensions>
        <parameterName>adam_eta</parameterName>
      </globalVariables>
      <globalVariables type="ModelRefInfoRepo.BuiltinParameter" uuid="3b12f462-ec05-475a-b18c-f28103bf253d">
        <dimensions>1</dimensions>
        <dimensions>1</dimensions>
        <isUsed>true</isUsed>
        <netSVCE>true</netSVCE>
        <numDimensions>2</numDimensions>
        <parameterName>adamax_beta_1</parameterName>
      </globalVariables>
      <globalVariables type="ModelRefInfoRepo.BuiltinParameter" uuid="9af95407-6684-4e39-a357-4cbe14c77b6a">
        <dimensions>1</dimensions>
        <dimensions>1</dimensions>
        <isUsed>true</isUsed>
        <netSVCE>true</netSVCE>
        <numDimensions>2</numDimensions>
        <parameterName>adamax_beta_2</parameterName>
      </globalVariables>
      <globalVariables type="ModelRefInfoRepo.BuiltinParameter" uuid="fc4739a0-1531-4709-921a-15e79b185ca6">
        <dimensions>1</dimensions>
        <dimensions>1</dimensions>
        <isUsed>true</isUsed>
        <netSVCE>true</netSVCE>
        <numDimensions>2</numDimensions>
        <parameterName>adamax_eta</parameterName>
      </globalVariables>
      <globalVariables type="ModelRefInfoRepo.BuiltinParameter" uuid="5c649b92-5922-40eb-bb02-91d1fa1987f9">
        <dimensions>1</dimensions>
        <dimensions>1</dimensions>
        <isUsed>true</isUsed>
        <netSVCE>true</netSVCE>
        <numDimensions>2</numDimensions>
        <parameterName>b0</parameterName>
      </globalVariables>
      <globalVariables type="ModelRefInfoRepo.BuiltinParameter" uuid="fa774527-ed72-4e82-82c5-112b996ec729">
        <dimensions>1</dimensions>
        <dimensions>1</dimensions>
        <isUsed>true</isUsed>
        <netSVCE>true</netSVCE>
        <numDimensions>2</numDimensions>
        <parameterName>b1</parameterName>
      </globalVariables>
      <globalVariables type="ModelRefInfoRepo.BuiltinParameter" uuid="193d500a-55da-4d10-a742-44d2ae31791a">
        <dimensions>1</dimensions>
        <dimensions>1</dimensions>
        <isUsed>true</isUsed>
        <netSVCE>true</netSVCE>
        <numDimensions>2</numDimensions>
        <parameterName>b2</parameterName>
      </globalVariables>
      <globalVariables type="ModelRefInfoRepo.BuiltinParameter" uuid="b617afb9-0af8-4663-b649-ef7f8846ed7c">
        <dimensions>1</dimensions>
        <dimensions>1</dimensions>
        <isUsed>true</isUsed>
        <netSVCE>true</netSVCE>
        <numDimensions>2</numDimensions>
        <parameterName>b3</parameterName>
      </globalVariables>
      <globalVariables type="ModelRefInfoRepo.BuiltinParameter" uuid="f3bff1fd-ad61-4f7b-80ec-0e564f0d7ec6">
        <dimensions>1</dimensions>
        <dimensions>1</dimensions>
        <isUsed>true</isUsed>
        <netSVCE>true</netSVCE>
        <numDimensions>2</numDimensions>
        <parameterName>baseRate</parameterName>
      </globalVariables>
      <globalVariables type="ModelRefInfoRepo.BuiltinParameter" uuid="d17ab6bb-619b-4ad9-8ef3-ddede9769885">
        <dimensions>1</dimensions>
        <dimensions>1</dimensions>
        <isUsed>true</isUsed>
        <netSVCE>true</netSVCE>
        <numDimensions>2</numDimensions>
        <parameterName>batch_eta</parameterName>
      </globalVariables>
      <globalVariables type="ModelRefInfoRepo.BuiltinParameter" uuid="f9e58bac-099e-4b67-bff9-f00446d08d81">
        <dimensions>1</dimensions>
        <dimensions>3</dimensions>
        <isUsed>true</isUsed>
        <netSVCE>true</netSVCE>
        <numDimensions>2</numDimensions>
        <parameterName>drop_states_BLACK</parameterName>
      </globalVariables>
      <globalVariables type="ModelRefInfoRepo.BuiltinParameter" uuid="f7b54e04-0f77-4835-8441-2b72da9344d8">
        <dimensions>1</dimensions>
        <dimensions>3</dimensions>
        <isUsed>true</isUsed>
        <netSVCE>true</netSVCE>
        <numDimensions>2</numDimensions>
        <parameterName>drop_states_BLUE</parameterName>
      </globalVariables>
      <globalVariables type="ModelRefInfoRepo.BuiltinParameter" uuid="9a26319f-6cd2-429a-b1cd-9fabf49e4086">
        <dimensions>1</dimensions>
        <dimensions>3</dimensions>
        <isUsed>true</isUsed>
        <netSVCE>true</netSVCE>
        <numDimensions>2</numDimensions>
        <parameterName>drop_states_RED</parameterName>
      </globalVariables>
      <globalVariables type="ModelRefInfoRepo.BuiltinParameter" uuid="cdd7d56f-f7a6-42a6-9ea4-c33eb72d22b1">
        <dimensions>1</dimensions>
        <dimensions>1</dimensions>
        <isUsed>true</isUsed>
        <netSVCE>true</netSVCE>
        <numDimensions>2</numDimensions>
        <parameterName>end_time_black</parameterName>
      </globalVariables>
      <globalVariables type="ModelRefInfoRepo.BuiltinParameter" uuid="999ec1ba-4f3b-41b4-959a-19c28cf78d3c">
        <dimensions>1</dimensions>
        <dimensions>1</dimensions>
        <isUsed>true</isUsed>
        <netSVCE>true</netSVCE>
        <numDimensions>2</numDimensions>
        <parameterName>end_time_blue</parameterName>
      </globalVariables>
      <globalVariables type="ModelRefInfoRepo.BuiltinParameter" uuid="cc8960cc-b434-47bb-8975-8ed555f4756c">
        <dimensions>1</dimensions>
        <dimensions>3</dimensions>
        <isUsed>true</isUsed>
        <netSVCE>true</netSVCE>
        <numDimensions>2</numDimensions>
        <parameterName>home_states_BLACK</parameterName>
      </globalVariables>
      <globalVariables type="ModelRefInfoRepo.BuiltinParameter" uuid="99c9a2e9-8748-4cd3-a615-b8ce39b65265">
        <dimensions>1</dimensions>
        <dimensions>3</dimensions>
        <isUsed>true</isUsed>
        <netSVCE>true</netSVCE>
        <numDimensions>2</numDimensions>
        <parameterName>home_states_BLUE</parameterName>
      </globalVariables>
      <globalVariables type="ModelRefInfoRepo.BuiltinParameter" uuid="0fe58b3f-d3ad-4d0b-9f38-40099f1eedd8">
        <dimensions>1</dimensions>
        <dimensions>3</dimensions>
        <isUsed>true</isUsed>
        <netSVCE>true</netSVCE>
        <numDimensions>2</numDimensions>
        <parameterName>home_states_RED</parameterName>
      </globalVariables>
      <globalVariables type="ModelRefInfoRepo.BuiltinParameter" uuid="04d507f8-bc5c-4ca2-94ff-312154b723e2">
        <dimensions>1</dimensions>
        <dimensions>3</dimensions>
        <isUsed>true</isUsed>
        <netSVCE>true</netSVCE>
        <numDimensions>2</numDimensions>
        <parameterName>init_states_BLACK</parameterName>
      </globalVariables>
      <globalVariables type="ModelRefInfoRepo.BuiltinParameter" uuid="120a1ebc-a9da-4fad-a2e4-481173a0a19a">
        <dimensions>1</dimensions>
        <dimensions>3</dimensions>
        <isUsed>true</isUsed>
        <netSVCE>true</netSVCE>
        <numDimensions>2</numDimensions>
        <parameterName>init_states_BLUE</parameterName>
      </globalVariables>
      <globalVariables type="ModelRefInfoRepo.BuiltinParameter" uuid="1853669a-33ae-4e4d-8707-c568550e8a63">
        <dimensions>1</dimensions>
        <dimensions>3</dimensions>
        <isUsed>true</isUsed>
        <netSVCE>true</netSVCE>
        <numDimensions>2</numDimensions>
        <parameterName>init_states_RED</parameterName>
      </globalVariables>
      <globalVariables type="ModelRefInfoRepo.BuiltinParameter" uuid="be60cfe2-0a3f-46be-84de-8382e97e6f59">
        <dimensions>3</dimensions>
        <dimensions>6</dimensions>
        <isUsed>true</isUsed>
        <netSVCE>true</netSVCE>
        <numDimensions>2</numDimensions>
        <parameterName>k</parameterName>
      </globalVariables>
      <globalVariables type="ModelRefInfoRepo.BuiltinParameter" uuid="634bc482-cb9b-4b9d-8400-6e791ada8dc9">
        <dimensions>1</dimensions>
        <dimensions>1</dimensions>
        <isUsed>true</isUsed>
        <netSVCE>true</netSVCE>
        <numDimensions>2</numDimensions>
        <parameterName>k_1_0</parameterName>
      </globalVariables>
      <globalVariables type="ModelRefInfoRepo.BuiltinParameter" uuid="c2c8e441-6efd-451f-ba35-a7379e4dbc42">
        <dimensions>1</dimensions>
        <dimensions>1</dimensions>
        <isUsed>true</isUsed>
        <netSVCE>true</netSVCE>
        <numDimensions>2</numDimensions>
        <parameterName>k_1_t_0</parameterName>
      </globalVariables>
      <globalVariables type="ModelRefInfoRepo.BuiltinParameter" uuid="f283a98f-36ca-453e-aa63-27cbcecc6e1a">
        <dimensions>1</dimensions>
        <dimensions>1</dimensions>
        <isUsed>true</isUsed>
        <netSVCE>true</netSVCE>
        <numDimensions>2</numDimensions>
        <parameterName>k_2_0</parameterName>
      </globalVariables>
      <globalVariables type="ModelRefInfoRepo.BuiltinParameter" uuid="ff3e65fd-adcd-429a-b58a-9ac41e408eed">
        <dimensions>1</dimensions>
        <dimensions>1</dimensions>
        <isUsed>true</isUsed>
        <netSVCE>true</netSVCE>
        <numDimensions>2</numDimensions>
        <parameterName>k_2_t_0</parameterName>
      </globalVariables>
      <globalVariables type="ModelRefInfoRepo.BuiltinParameter" uuid="713da59a-59ac-4c14-8a5e-737c77f17e7d">
        <dimensions>1</dimensions>
        <dimensions>1</dimensions>
        <isUsed>true</isUsed>
        <netSVCE>true</netSVCE>
        <numDimensions>2</numDimensions>
        <parameterName>ka</parameterName>
      </globalVariables>
      <globalVariables type="ModelRefInfoRepo.BuiltinParameter" uuid="d1553442-3f3f-412a-9b90-ee83b7aee405">
        <dimensions>1</dimensions>
        <dimensions>1</dimensions>
        <isUsed>true</isUsed>
        <netSVCE>true</netSVCE>
        <numDimensions>2</numDimensions>
        <parameterName>kr</parameterName>
      </globalVariables>
      <globalVariables type="ModelRefInfoRepo.BuiltinParameter" uuid="2abe7641-eac1-4485-bf98-deda9c6cb20e">
        <dimensions>1</dimensions>
        <dimensions>1</dimensions>
        <isUsed>true</isUsed>
        <netSVCE>true</netSVCE>
        <numDimensions>2</numDimensions>
        <parameterName>lambda1</parameterName>
      </globalVariables>
      <globalVariables type="ModelRefInfoRepo.BuiltinParameter" uuid="dcb8f646-ff0b-4a24-a265-dc7828f2c069">
        <dimensions>1</dimensions>
        <dimensions>1</dimensions>
        <isUsed>true</isUsed>
        <netSVCE>true</netSVCE>
        <numDimensions>2</numDimensions>
        <parameterName>lambda12</parameterName>
      </globalVariables>
      <globalVariables type="ModelRefInfoRepo.BuiltinParameter" uuid="428d663f-2ce7-426d-972c-15c0db1c7f39">
        <dimensions>1</dimensions>
        <dimensions>1</dimensions>
        <isUsed>true</isUsed>
        <netSVCE>true</netSVCE>
        <numDimensions>2</numDimensions>
        <parameterName>lambda12_t</parameterName>
      </globalVariables>
      <globalVariables type="ModelRefInfoRepo.BuiltinParameter" uuid="772f2200-9a92-45f0-ae21-b054203f7f48">
        <dimensions>1</dimensions>
        <dimensions>1</dimensions>
        <isUsed>true</isUsed>
        <netSVCE>true</netSVCE>
        <numDimensions>2</numDimensions>
        <parameterName>lambda1_t</parameterName>
      </globalVariables>
      <globalVariables type="ModelRefInfoRepo.BuiltinParameter" uuid="291e91df-92f6-4396-aa0b-2b58edd21e23">
        <dimensions>1</dimensions>
        <dimensions>1</dimensions>
        <isUsed>true</isUsed>
        <netSVCE>true</netSVCE>
        <numDimensions>2</numDimensions>
        <parameterName>lambda2</parameterName>
      </globalVariables>
      <globalVariables type="ModelRefInfoRepo.BuiltinParameter" uuid="fb916446-0eb8-4ba4-87cd-0005fe9c1af0">
        <dimensions>1</dimensions>
        <dimensions>1</dimensions>
        <isUsed>true</isUsed>
        <netSVCE>true</netSVCE>
        <numDimensions>2</numDimensions>
        <parameterName>lambda2_t</parameterName>
      </globalVariables>
      <globalVariables type="ModelRefInfoRepo.BuiltinParameter" uuid="88ff5af9-c47d-4576-9372-f94da3e13f57">
        <dimensions>1</dimensions>
        <dimensions>1</dimensions>
        <isUsed>true</isUsed>
        <netSVCE>true</netSVCE>
        <numDimensions>2</numDimensions>
        <parameterName>mBLACK</parameterName>
      </globalVariables>
      <globalVariables type="ModelRefInfoRepo.BuiltinParameter" uuid="c02c16c6-2938-4957-8789-dae355398de9">
        <dimensions>1</dimensions>
        <dimensions>1</dimensions>
        <isUsed>true</isUsed>
        <netSVCE>true</netSVCE>
        <numDimensions>2</numDimensions>
        <parameterName>mBLUE</parameterName>
      </globalVariables>
      <globalVariables type="ModelRefInfoRepo.BuiltinParameter" uuid="8ded5efe-52e1-47e3-b188-2ff73688b172">
        <dimensions>1</dimensions>
        <dimensions>1</dimensions>
        <isUsed>true</isUsed>
        <netSVCE>true</netSVCE>
        <numDimensions>2</numDimensions>
        <parameterName>mDIST</parameterName>
      </globalVariables>
      <globalVariables type="ModelRefInfoRepo.BuiltinParameter" uuid="f9d359ec-f84b-480c-b006-b2eacf28a24f">
        <dimensions>1</dimensions>
        <dimensions>1</dimensions>
        <isUsed>true</isUsed>
        <netSVCE>true</netSVCE>
        <numDimensions>2</numDimensions>
        <parameterName>mEE</parameterName>
      </globalVariables>
      <globalVariables type="ModelRefInfoRepo.BuiltinParameter" uuid="c4edf9bb-7cda-452c-98d6-19b3524d363e">
        <dimensions>1</dimensions>
        <dimensions>1</dimensions>
        <isUsed>true</isUsed>
        <netSVCE>true</netSVCE>
        <numDimensions>2</numDimensions>
        <parameterName>mPROX</parameterName>
      </globalVariables>
      <globalVariables type="ModelRefInfoRepo.BuiltinParameter" uuid="d65ae90b-e5a2-46b2-8639-910ebbbcd540">
        <dimensions>1</dimensions>
        <dimensions>1</dimensions>
        <isUsed>true</isUsed>
        <netSVCE>true</netSVCE>
        <numDimensions>2</numDimensions>
        <parameterName>mRED</parameterName>
      </globalVariables>
      <globalVariables type="ModelRefInfoRepo.BuiltinParameter" uuid="03fa1369-311f-463e-a481-2e0e3762a305">
        <dimensions>1</dimensions>
        <dimensions>1</dimensions>
        <isUsed>true</isUsed>
        <netSVCE>true</netSVCE>
        <numDimensions>2</numDimensions>
        <parameterName>momentum_eta</parameterName>
      </globalVariables>
      <globalVariables type="ModelRefInfoRepo.BuiltinParameter" uuid="f72fd4d3-887a-4917-bd23-8e0495aea73c">
        <dimensions>1</dimensions>
        <dimensions>1</dimensions>
        <isUsed>true</isUsed>
        <netSVCE>true</netSVCE>
        <numDimensions>2</numDimensions>
        <parameterName>momentum_gamma</parameterName>
      </globalVariables>
      <globalVariables type="ModelRefInfoRepo.BuiltinParameter" uuid="e9953897-7b44-4710-836f-a704873491f4">
        <dimensions>1</dimensions>
        <dimensions>1</dimensions>
        <isUsed>true</isUsed>
        <netSVCE>true</netSVCE>
        <numDimensions>2</numDimensions>
        <parameterName>nesterov_eta</parameterName>
      </globalVariables>
      <globalVariables type="ModelRefInfoRepo.BuiltinParameter" uuid="d38a61f5-20da-4abd-ae5d-864ff5973d5d">
        <dimensions>1</dimensions>
        <dimensions>1</dimensions>
        <isUsed>true</isUsed>
        <netSVCE>true</netSVCE>
        <numDimensions>2</numDimensions>
        <parameterName>nesterov_gamma</parameterName>
      </globalVariables>
      <globalVariables type="ModelRefInfoRepo.BuiltinParameter" uuid="afae6e47-834a-464b-a918-a8c93a8c3368">
        <dimensions>1</dimensions>
        <dimensions>1</dimensions>
        <isUsed>true</isUsed>
        <netSVCE>true</netSVCE>
        <numDimensions>2</numDimensions>
        <parameterName>noise_variance_BLACK</parameterName>
      </globalVariables>
      <globalVariables type="ModelRefInfoRepo.BuiltinParameter" uuid="afb18e4e-e61a-41e0-ab8e-c40d2f040205">
        <dimensions>1</dimensions>
        <dimensions>1</dimensions>
        <isUsed>true</isUsed>
        <netSVCE>true</netSVCE>
        <numDimensions>2</numDimensions>
        <parameterName>noise_variance_BLUE</parameterName>
      </globalVariables>
      <globalVariables type="ModelRefInfoRepo.BuiltinParameter" uuid="4ee3c7d1-6014-46f8-bef2-5004f116ea39">
        <dimensions>1</dimensions>
        <dimensions>1</dimensions>
        <isUsed>true</isUsed>
        <netSVCE>true</netSVCE>
        <numDimensions>2</numDimensions>
        <parameterName>noise_variance_RED</parameterName>
      </globalVariables>
      <globalVariables type="ModelRefInfoRepo.BuiltinParameter" uuid="9d277260-0ab4-4b3e-8bbd-857c639ec8c6">
        <dimensions>1</dimensions>
        <dimensions>1</dimensions>
        <isUsed>true</isUsed>
        <netSVCE>true</netSVCE>
        <numDimensions>2</numDimensions>
        <parameterName>p</parameterName>
      </globalVariables>
      <globalVariables type="ModelRefInfoRepo.BuiltinParameter" uuid="3ff730f6-edb6-4cc1-922f-8e4cab519541">
        <dimensions>1</dimensions>
        <dimensions>1</dimensions>
        <isUsed>true</isUsed>
        <netSVCE>true</netSVCE>
        <numDimensions>2</numDimensions>
        <parameterName>p_t</parameterName>
      </globalVariables>
      <globalVariables type="ModelRefInfoRepo.BuiltinParameter" uuid="04a0cdda-a3e2-4978-b9e3-f59c31e595e0">
        <dimensions>1</dimensions>
        <dimensions>1</dimensions>
        <isUsed>true</isUsed>
        <netSVCE>true</netSVCE>
        <numDimensions>2</numDimensions>
        <parameterName>platformSelection</parameterName>
      </globalVariables>
      <globalVariables type="ModelRefInfoRepo.BuiltinParameter" uuid="e730f5ba-0068-4ba1-8f56-3fba98cfdf31">
        <dimensions>1</dimensions>
        <dimensions>1</dimensions>
        <isUsed>true</isUsed>
        <netSVCE>true</netSVCE>
        <numDimensions>2</numDimensions>
        <parameterName>psi</parameterName>
      </globalVariables>
      <globalVariables type="ModelRefInfoRepo.BuiltinParameter" uuid="8b2161bd-1a1f-4ef6-bfb8-605f834ba2da">
        <dimensions>1</dimensions>
        <dimensions>1</dimensions>
        <isUsed>true</isUsed>
        <netSVCE>true</netSVCE>
        <numDimensions>2</numDimensions>
        <parameterName>r_hold</parameterName>
      </globalVariables>
      <globalVariables type="ModelRefInfoRepo.BuiltinParameter" uuid="aefda256-9a05-40a1-aa87-a6f9b32330f2">
        <dimensions>1</dimensions>
        <dimensions>1</dimensions>
        <isUsed>true</isUsed>
        <netSVCE>true</netSVCE>
        <numDimensions>2</numDimensions>
        <parameterName>r_off</parameterName>
      </globalVariables>
      <globalVariables type="ModelRefInfoRepo.BuiltinParameter" uuid="259620a0-326c-46a9-9d0c-8f338189513a">
        <dimensions>1</dimensions>
        <dimensions>5</dimensions>
        <isUsed>true</isUsed>
        <netSVCE>true</netSVCE>
        <numDimensions>2</numDimensions>
        <parameterName>shape</parameterName>
      </globalVariables>
      <globalVariables type="ModelRefInfoRepo.BuiltinParameter" uuid="76b8dafe-24fc-4efe-8be1-097251c18484">
        <dimensions>1</dimensions>
        <dimensions>1</dimensions>
        <isUsed>true</isUsed>
        <netSVCE>true</netSVCE>
        <numDimensions>2</numDimensions>
        <parameterName>sigma</parameterName>
      </globalVariables>
      <globalVariables type="ModelRefInfoRepo.BuiltinParameter" uuid="5986943c-2ea7-4228-ac04-0ae92681f040">
        <dimensions>1</dimensions>
        <dimensions>1</dimensions>
        <isUsed>true</isUsed>
        <netSVCE>true</netSVCE>
        <numDimensions>2</numDimensions>
        <parameterName>simMode</parameterName>
      </globalVariables>
      <globalVariables type="ModelRefInfoRepo.BuiltinParameter" uuid="91b3dd8d-9bd3-4646-9cff-4d67a0e031fe">
        <dimensions>1</dimensions>
        <dimensions>1</dimensions>
        <isUsed>true</isUsed>
        <netSVCE>true</netSVCE>
        <numDimensions>2</numDimensions>
        <parameterName>thruster_count_threshold</parameterName>
      </globalVariables>
      <globalVariables type="ModelRefInfoRepo.BuiltinParameter" uuid="1b47a099-6036-4554-bce4-63b039e98eae">
        <dimensions>8</dimensions>
        <dimensions>1</dimensions>
        <isUsed>true</isUsed>
        <netSVCE>true</netSVCE>
        <numDimensions>2</numDimensions>
        <parameterName>thruster_dist2CG_BLACK</parameterName>
      </globalVariables>
      <globalVariables type="ModelRefInfoRepo.BuiltinParameter" uuid="2b83b74c-0436-4441-959a-99b7ecadf0e8">
        <dimensions>8</dimensions>
        <dimensions>1</dimensions>
        <isUsed>true</isUsed>
        <netSVCE>true</netSVCE>
        <numDimensions>2</numDimensions>
        <parameterName>thruster_dist2CG_BLUE</parameterName>
      </globalVariables>
      <globalVariables type="ModelRefInfoRepo.BuiltinParameter" uuid="66ef83b4-2c9e-425c-b6cf-c723eb254cac">
        <dimensions>8</dimensions>
        <dimensions>1</dimensions>
        <isUsed>true</isUsed>
        <netSVCE>true</netSVCE>
        <numDimensions>2</numDimensions>
        <parameterName>thruster_dist2CG_RED</parameterName>
      </globalVariables>
      <globalVariables type="ModelRefInfoRepo.BuiltinParameter" uuid="eb1c8b74-552d-4644-bd91-3db0e55c8ad1">
        <dimensions>1</dimensions>
        <dimensions>1</dimensions>
        <isUsed>true</isUsed>
        <netSVCE>true</netSVCE>
        <numDimensions>2</numDimensions>
        <parameterName>xLength</parameterName>
      </globalVariables>
      <globalVariables type="ModelRefInfoRepo.BuiltinParameter" uuid="7df4923b-545a-4513-a4d7-d853071fd385">
        <dimensions>1</dimensions>
        <dimensions>1</dimensions>
        <isUsed>true</isUsed>
        <netSVCE>true</netSVCE>
        <numDimensions>2</numDimensions>
        <parameterName>yLength</parameterName>
      </globalVariables>
    </interfaceParameterInfo>
    <messageInfo type="ModelRefInfoRepo.MessageInformation" uuid="f687e6f1-5542-4d9f-89f8-78b44bd8cbd1"/>
    <methodInfo type="ModelRefInfoRepo.MethodExistenceInfo" uuid="5739b022-a130-43f3-8e70-9f8d287af5eb">
      <hasDerivMethod>true</hasDerivMethod>
      <hasEnableMethod>true</hasEnableMethod>
      <hasForcingFunctionMethod>true</hasForcingFunctionMethod>
      <hasSystemInitializeMethod>true</hasSystemInitializeMethod>
      <hasSystemResetMethod>true</hasSystemResetMethod>
      <hasTerminateMethod>true</hasTerminateMethod>
      <hasUpdateMethod>true</hasUpdateMethod>
    </methodInfo>
    <periodicEventPortUnsupportedBlockInfo type="ModelRefInfoRepo.PeriodicEventPortUnsupportedBlockInfo" uuid="54af2e3d-5db2-4494-8541-d11968ffc656">
      <multiRateSubsystems>APF_Path_Planning_2023a/PhaseSpace Camera Code/Use Hardware to Obtain States/Adjust Time/Enabled Subsystem1</multiRateSubsystems>
    </periodicEventPortUnsupportedBlockInfo>
    <portGroupsRequireSameRate type="ModelRefInfoRepo.PortGroupsRequireSameRate" uuid="f996e20c-d141-403d-a799-af1727881bd7">
      <DSMPortGroups type="ModelRefInfoRepo.NameToPortGroupIdxVectMap" uuid="62b52482-313e-40be-ae3f-de014478c764"/>
      <GlobalDSMPortGroups type="ModelRefInfoRepo.NameToPortGroupIdxVectMap" uuid="5231f44e-93cd-48ea-b010-87aa70412b7e"/>
      <mergedPortGroups type="ModelRefInfoRepo.NameToPortGroupIdxVectMap" uuid="a06f1a44-ddf7-42ef-99c5-0ef5fa9ef60d"/>
    </portGroupsRequireSameRate>
    <rateBasedMdlGlobalDSMRateSpec type="ModelRefInfoRepo.GlobalDSMRateSpecMap" uuid="5877f102-c6fb-40a8-9b0a-1fa8b32b4eac"/>
    <rateSpecOfGlobalDSMAccessedByDescExpFcnMdlMap type="ModelRefInfoRepo.GlobalDSMRateSpecMap" uuid="a4b9c376-77e6-48c9-8d7d-2577842c3cd0"/>
    <rootBlockDiagramInterface type="ci.Model" uuid="e0eee15a-d9cf-40fa-9cb5-67feaf52c490">
      <p_RootComponentInterface type="ci.ComponentInterface" uuid="22903a56-99b5-4b95-ad80-9033bf810190">
        <p_Name>APF_Path_Planning_2023a</p_Name>
        <p_Type>ROOT</p_Type>
      </p_RootComponentInterface>
    </rootBlockDiagramInterface>
    <simulinkFunctions type="ModelRefInfoRepo.SimulinkFunctions" uuid="199fc8a0-a894-424f-b3a4-34c61554723a">
      <compSimulinkFunctionCatalog></compSimulinkFunctionCatalog>
    </simulinkFunctions>
    <sltpContext type="sltp.mm.core.Context" uuid="eaa72d88-4ee5-416d-b060-e92534399baf">
      <priorityDirection>HighNumberLast</priorityDirection>
      <unusedTaskIds>1</unusedTaskIds>
      <defaultEventBehavior type="sltp.mm.core.EventBehavior" uuid="d7ab87b1-5e71-4ca0-9d82-f03c5bd9acc2"/>
      <editorState type="sltp.mm.core.EditorState" uuid="dfddbac0-357d-476b-aee8-f6ce847b5b79">
        <isSynchronized>true</isSynchronized>
        <panelState type="sltp.mm.core.EditorPanelState" uuid="ce5f0e47-f930-4581-a1d3-2284783b58ef"/>
      </editorState>
      <rootTask type="sltp.mm.core.Task" uuid="d68bf30b-f682-4bfc-92a1-8148c2d0e839">
        <context type="sltp.mm.core.Context" uuid="eaa72d88-4ee5-416d-b060-e92534399baf"/>
        <explicit>false</explicit>
        <name>Default</name>
        <priority>-2147483648</priority>
        <subgraph type="sltp.mm.core.Graph" uuid="d49cbe55-bd86-4672-a486-46c034e89138">
          <tasks type="sltp.mm.core.Task" uuid="ed6bf1c7-27d5-4dcc-a898-20979f8abf93">
            <baseTask>true</baseTask>
            <context type="sltp.mm.core.Context" uuid="eaa72d88-4ee5-416d-b060-e92534399baf"/>
            <explicit>false</explicit>
            <id>2</id>
            <isTimed>true</isTimed>
            <name>Cont</name>
            <priority>40</priority>
            <rates type="sltp.mm.core.Rate" uuid="fae0f3fe-82a2-40c4-a69f-c3ba5cff4e6b">
              <annotation>Cont</annotation>
              <color>255</color>
              <hasBlocks>true</hasBlocks>
              <identifier>Continuous00</identifier>
              <rateIndex>0</rateIndex>
              <rateSpec type="sltp.mm.core.RateSpec">
                <period>0.0</period>
              </rateSpec>
              <sti>0</sti>
            </rates>
            <rates type="sltp.mm.core.Rate" uuid="8a3aca56-bb2b-46c0-b596-5c2f67a1f37b">
              <annotation>D1</annotation>
              <color>-436207361</color>
              <hasBlocks>true</hasBlocks>
              <rateIndex>1</rateIndex>
              <rateSpec type="sltp.mm.core.RateSpec">
                <period>.01</period>
              </rateSpec>
              <sti>1</sti>
            </rates>
          </tasks>
        </subgraph>
      </rootTask>
    </sltpContext>
    <stateWriterToOwnerMap type="ModelRefInfoRepo.StateWriterInfo" uuid="b36b68f1-ff63-42f3-b8a0-1cfc9412e992"/>
    <stoClientDataRegistry type="sto.ClientDataRegistry" uuid="76c6241b-b510-46f9-84ae-d8021e9ab742">
      <dataSets type="sto.ClientClockNamedDataSet" uuid="171d4497-4431-4176-86e1-763c631b0dcd">
        <tag>sltpEvents</tag>
      </dataSets>
      <dataSets type="sto.ClientTaskHierarchyElementNamedDataSet" uuid="5132d7f4-7261-4b21-8338-ed6a97db4d08">
        <tag>sltpTaskGroups</tag>
      </dataSets>
      <dataSets type="sto.ClientTaskHierarchyElementNamedDataSet" uuid="c0ed0dcf-e045-44f3-b7bd-e71269c8c646">
        <dSet type="ModelRefInfoRepo.SltpTaskData" uuid="2cfb9647-f3bb-4ea1-bdc4-01d5e12ae34d"/>
        <tSet type="ModelRefInfoRepo.SltpTaskData" uuid="2cfb9647-f3bb-4ea1-bdc4-01d5e12ae34d">
          <dataName>Cont</dataName>
          <linkedSet type="sto.ClientTaskHierarchyElementNamedDataSet" uuid="c0ed0dcf-e045-44f3-b7bd-e71269c8c646"/>
          <id type="sto.TaskHierarchyElementId">
            <clockId>APF_Path_Planning_2023a::defaultTimer</clockId>
            <id>_task0</id>
          </id>
        </tSet>
        <tag>sltpTasks</tag>
      </dataSets>
    </stoClientDataRegistry>
    <varTsUIDMap type="ModelRefInfoRepo.VarTsUIDMap" uuid="45628bd3-376d-4ac5-9064-c8d46e796540"/>
  </ModelRefInfoRepo.ModelRefInfoRoot>
</MF0>